[
  {
    "image_override": null,
    "rounds": [
      {
        "round_number": "1",
        "zones": [
          {
            "zone_id": "Zone01",
            "collectable_type_spawns": [
              {
                "collectable_type": "oriole",
                "spawn_value": 100
              }
            ],
            "min_spawn_value": 100,
            "max_spawn_value": 100
          },
          {
            "zone_id": "Zone02",
            "collectable_type_spawns": [
              {
                "collectable_type": "oriole",
                "spawn_value": 100
              }
            ],
            "min_spawn_value": 100,
            "max_spawn_value": 100
          },
          {
            "zone_id": "Zone03",
            "collectable_type_spawns": [
              {
                "collectable_type": "oriole",
                "spawn_value": 100
              }
            ],
            "min_spawn_value": 100,
            "max_spawn_value": 100
          }
        ]
      },
      {
        "round_number": "2",
        "zones": [
          {
            "zone_id": "Zone01",
            "collectable_type_spawns": [
              {
                "collectable_type": "oriole",
                "spawn_value": 100
              }
            ],
            "min_spawn_value": 100,
            "max_spawn_value": 100
          },
          {
            "zone_id": "Zone02",
            "collectable_type_spawns": [
              {
                "collectable_type": "oriole",
                "spawn_value": 100
              }
            ],
            "min_spawn_value": 100,
            "max_spawn_value": 100
          },
          {
            "zone_id": "Zone03",
            "collectable_type_spawns": [
              {
                "collectable_type": "oriole",
                "spawn_value": 100
              }
            ],
            "min_spawn_value": 100,
            "max_spawn_value": 100
          }
        ]
      },
      {
        "round_number": "3",
        "zones": [
          {
            "zone_id": "Zone01",
            "collectable_type_spawns": [
              {
                "collectable_type": "oriole",
                "spawn_value": 100
              }
            ],
            "min_spawn_value": 100,
            "max_spawn_value": 100
          },
          {
            "zone_id": "Zone02",
            "collectable_type_spawns": [
              {
                "collectable_type": "oriole",
                "spawn_value": 100
              }
            ],
            "min_spawn_value": 100,
            "max_spawn_value": 100
          },
          {
            "zone_id": "Zone03",
            "collectable_type_spawns": [
              {
                "collectable_type": "oriole",
                "spawn_value": 100
              }
            ],
            "min_spawn_value": 100,
            "max_spawn_value": 100
          }
        ]
      },
      {
        "round_number": "4",
        "zones": [
          {
            "zone_id": "Zone01",
            "collectable_type_spawns": [
              {
                "collectable_type": "oriole",
                "spawn_value": 100
              }
            ],
            "min_spawn_value": 100,
            "max_spawn_value": 100
          },
          {
            "zone_id": "Zone02",
            "collectable_type_spawns": [
              {
                "collectable_type": "oriole",
                "spawn_value": 100
              }
            ],
            "min_spawn_value": 100,
            "max_spawn_value": 100
          },
          {
            "zone_id": "Zone03",
            "collectable_type_spawns": [
              {
                "collectable_type": "oriole",
                "spawn_value": 100
              }
            ],
            "min_spawn_value": 100,
            "max_spawn_value": 100
          }
        ]
      },
      {
        "round_number": "Final",
        "zones": [
          {
            "zone_id": "Zone01",
            "collectable_type_spawns": [
              {
                "collectable_type": "oriole",
                "spawn_value": 100
              }
            ],
            "min_spawn_value": 100,
            "max_spawn_value": 100
          },
          {
            "zone_id": "Zone02",
            "collectable_type_spawns": [
              {
                "collectable_type": "oriole",
                "spawn_value": 100
              }
            ],
            "min_spawn_value": 100,
            "max_spawn_value": 100
          },
          {
            "zone_id": "Zone03",
            "collectable_type_spawns": [
              {
                "collectable_type": "oriole",
                "spawn_value": 100
              }
            ],
            "min_spawn_value": 100,
            "max_spawn_value": 100
          }
        ]
      }
    ],
    "id": "default_lm_three_zones"
  },
  {
    "image_override": "ui_collectibles_potoo_combined",
    "rounds": [
      {
        "round_number": "1",
        "zones": [
          {
            "zone_id": "Zone01",
            "collectable_type_spawns": [
              {
                "collectable_type": "co_potoo_01",
                "spawn_value": 50
              },
              {
                "collectable_type": "co_potoo_02",
                "spawn_value": 50
              }
            ],
            "min_spawn_value": 10,
            "max_spawn_value": 20
          },
          {
            "zone_id": "Zone02",
            "collectable_type_spawns": [
              {
                "collectable_type": "co_potoo_01",
                "spawn_value": 50
              },
              {
                "collectable_type": "co_potoo_02",
                "spawn_value": 50
              }
            ],
            "min_spawn_value": 20,
            "max_spawn_value": 30
          },
          {
            "zone_id": "Zone03",
            "collectable_type_spawns": [
              {
                "collectable_type": "co_potoo_01",
                "spawn_value": 50
              },
              {
                "collectable_type": "co_potoo_02",
                "spawn_value": 50
              }
            ],
            "min_spawn_value": 30,
            "max_spawn_value": 40
          }
        ]
      },
      {
        "round_number": "2",
        "zones": [
          {
            "zone_id": "Zone01",
            "collectable_type_spawns": [
              {
                "collectable_type": "co_potoo_01",
                "spawn_value": 40
              },
              {
                "collectable_type": "co_potoo_02",
                "spawn_value": 60
              }
            ],
            "min_spawn_value": 15,
            "max_spawn_value": 25
          },
          {
            "zone_id": "Zone02",
            "collectable_type_spawns": [
              {
                "collectable_type": "co_potoo_01",
                "spawn_value": 60
              },
              {
                "collectable_type": "co_potoo_02",
                "spawn_value": 40
              }
            ],
            "min_spawn_value": 25,
            "max_spawn_value": 35
          },
          {
            "zone_id": "Zone03",
            "collectable_type_spawns": [
              {
                "collectable_type": "co_potoo_01",
                "spawn_value": 40
              },
              {
                "collectable_type": "co_potoo_02",
                "spawn_value": 60
              }
            ],
            "min_spawn_value": 35,
            "max_spawn_value": 45
          }
        ]
      },
      {
        "round_number": "3",
        "zones": [
          {
            "zone_id": "Zone01",
            "collectable_type_spawns": [
              {
                "collectable_type": "co_potoo_01",
                "spawn_value": 70
              },
              {
                "collectable_type": "co_potoo_02",
                "spawn_value": 30
              }
            ],
            "min_spawn_value": 20,
            "max_spawn_value": 30
          },
          {
            "zone_id": "Zone02",
            "collectable_type_spawns": [
              {
                "collectable_type": "co_potoo_01",
                "spawn_value": 70
              },
              {
                "collectable_type": "co_potoo_02",
                "spawn_value": 30
              }
            ],
            "min_spawn_value": 30,
            "max_spawn_value": 40
          },
          {
            "zone_id": "Zone03",
            "collectable_type_spawns": [
              {
                "collectable_type": "co_potoo_01",
                "spawn_value": 70
              },
              {
                "collectable_type": "co_potoo_02",
                "spawn_value": 30
              }
            ],
            "min_spawn_value": 40,
            "max_spawn_value": 50
          }
        ]
      },
      {
        "round_number": "4",
        "zones": [
          {
            "zone_id": "Zone01",
            "collectable_type_spawns": [
              {
                "collectable_type": "co_potoo_01",
                "spawn_value": 30
              },
              {
                "collectable_type": "co_potoo_02",
                "spawn_value": 70
              }
            ],
            "min_spawn_value": 30,
            "max_spawn_value": 40
          },
          {
            "zone_id": "Zone02",
            "collectable_type_spawns": [
              {
                "collectable_type": "co_potoo_01",
                "spawn_value": 30
              },
              {
                "collectable_type": "co_potoo_02",
                "spawn_value": 70
              }
            ],
            "min_spawn_value": 40,
            "max_spawn_value": 50
          },
          {
            "zone_id": "Zone03",
            "collectable_type_spawns": [
              {
                "collectable_type": "co_potoo_01",
                "spawn_value": 30
              },
              {
                "collectable_type": "co_potoo_02",
                "spawn_value": 70
              }
            ],
            "min_spawn_value": 50,
            "max_spawn_value": 60
          }
        ]
      },
      {
        "round_number": "Final",
        "zones": [
          {
            "zone_id": "Zone01",
            "collectable_type_spawns": [
              {
                "collectable_type": "co_potoo_01",
                "spawn_value": 50
              },
              {
                "collectable_type": "co_potoo_02",
                "spawn_value": 50
              }
            ],
            "min_spawn_value": 40,
            "max_spawn_value": 50
          },
          {
            "zone_id": "Zone02",
            "collectable_type_spawns": [
              {
                "collectable_type": "co_potoo_01",
                "spawn_value": 50
              },
              {
                "collectable_type": "co_potoo_02",
                "spawn_value": 50
              }
            ],
            "min_spawn_value": 50,
            "max_spawn_value": 60
          },
          {
            "zone_id": "Zone03",
            "collectable_type_spawns": [
              {
                "collectable_type": "co_potoo_01",
                "spawn_value": 50
              },
              {
                "collectable_type": "co_potoo_02",
                "spawn_value": 50
              }
            ],
            "min_spawn_value": 60,
            "max_spawn_value": 70
          }
        ]
      }
    ],
    "id": "event_ss2_potoo"
  },
  {
    "image_override": null,
    "rounds": [
      {
        "round_number": "1",
        "zones": [
          {
            "zone_id": "Zone01",
            "collectable_type_spawns": [
              {
                "collectable_type": "oriole",
                "spawn_value": 100
              }
            ],
            "min_spawn_value": 33,
            "max_spawn_value": 39
          },
          {
            "zone_id": "Zone02",
            "collectable_type_spawns": [
              {
                "collectable_type": "oriole",
                "spawn_value": 100
              }
            ],
            "min_spawn_value": 28,
            "max_spawn_value": 34
          },
          {
            "zone_id": "Zone03",
            "collectable_type_spawns": [
              {
                "collectable_type": "oriole",
                "spawn_value": 100
              }
            ],
            "min_spawn_value": 50,
            "max_spawn_value": 56
          }
        ]
      },
      {
        "round_number": "2",
        "zones": [
          {
            "zone_id": "Zone01",
            "collectable_type_spawns": [
              {
                "collectable_type": "oriole",
                "spawn_value": 100
              }
            ],
            "min_spawn_value": 42,
            "max_spawn_value": 48
          },
          {
            "zone_id": "Zone02",
            "collectable_type_spawns": [
              {
                "collectable_type": "oriole",
                "spawn_value": 100
              }
            ],
            "min_spawn_value": 36,
            "max_spawn_value": 42
          },
          {
            "zone_id": "Zone03",
            "collectable_type_spawns": [
              {
                "collectable_type": "oriole",
                "spawn_value": 100
              }
            ],
            "min_spawn_value": 63,
            "max_spawn_value": 69
          }
        ]
      },
      {
        "round_number": "3",
        "zones": [
          {
            "zone_id": "Zone01",
            "collectable_type_spawns": [
              {
                "collectable_type": "oriole",
                "spawn_value": 100
              }
            ],
            "min_spawn_value": 42,
            "max_spawn_value": 48
          },
          {
            "zone_id": "Zone02",
            "collectable_type_spawns": [
              {
                "collectable_type": "oriole",
                "spawn_value": 100
              }
            ],
            "min_spawn_value": 36,
            "max_spawn_value": 42
          },
          {
            "zone_id": "Zone03",
            "collectable_type_spawns": [
              {
                "collectable_type": "oriole",
                "spawn_value": 100
              }
            ],
            "min_spawn_value": 63,
            "max_spawn_value": 69
          }
        ]
      },
      {
        "round_number": "4",
        "zones": [
          {
            "zone_id": "Zone01",
            "collectable_type_spawns": [
              {
                "collectable_type": "oriole",
                "spawn_value": 100
              }
            ],
            "min_spawn_value": 54,
            "max_spawn_value": 60
          },
          {
            "zone_id": "Zone02",
            "collectable_type_spawns": [
              {
                "collectable_type": "oriole",
                "spawn_value": 100
              }
            ],
            "min_spawn_value": 46,
            "max_spawn_value": 52
          },
          {
            "zone_id": "Zone03",
            "collectable_type_spawns": [
              {
                "collectable_type": "oriole",
                "spawn_value": 100
              }
            ],
            "min_spawn_value": 81,
            "max_spawn_value": 87
          }
        ]
      },
      {
        "round_number": "Final",
        "zones": [
          {
            "zone_id": "Zone01",
            "collectable_type_spawns": [
              {
                "collectable_type": "oriole",
                "spawn_value": 100
              }
            ],
            "min_spawn_value": 63,
            "max_spawn_value": 69
          },
          {
            "zone_id": "Zone02",
            "collectable_type_spawns": [
              {
                "collectable_type": "oriole",
                "spawn_value": 100
              }
            ],
            "min_spawn_value": 54,
            "max_spawn_value": 60
          },
          {
            "zone_id": "Zone03",
            "collectable_type_spawns": [
              {
                "collectable_type": "oriole",
                "spawn_value": 100
              }
            ],
            "min_spawn_value": 94,
            "max_spawn_value": 100
          }
        ]
      }
    ],
    "id": "oriole_three_zones"
  },
  {
    "image_override": "ui_collectables_parrot_combined",
    "rounds": [
      {
        "round_number": "1",
        "zones": [
          {
            "zone_id": "Zone01",
            "collectable_type_spawns": [
              {
                "collectable_type": "co_parrot_01",
                "spawn_value": 80
              },
              {
                "collectable_type": "co_parrot_02",
                "spawn_value": 20
              }
            ],
            "min_spawn_value": 33,
            "max_spawn_value": 39
          },
          {
            "zone_id": "Zone02",
            "collectable_type_spawns": [
              {
                "collectable_type": "co_parrot_01",
                "spawn_value": 80
              },
              {
                "collectable_type": "co_parrot_02",
                "spawn_value": 20
              }
            ],
            "min_spawn_value": 28,
            "max_spawn_value": 34
          },
          {
            "zone_id": "Zone03",
            "collectable_type_spawns": [
              {
                "collectable_type": "co_parrot_01",
                "spawn_value": 80
              },
              {
                "collectable_type": "co_parrot_02",
                "spawn_value": 20
              }
            ],
            "min_spawn_value": 50,
            "max_spawn_value": 56
          }
        ]
      },
      {
        "round_number": "2",
        "zones": [
          {
            "zone_id": "Zone01",
            "collectable_type_spawns": [
              {
                "collectable_type": "co_parrot_01",
                "spawn_value": 75
              },
              {
                "collectable_type": "co_parrot_02",
                "spawn_value": 25
              }
            ],
            "min_spawn_value": 42,
            "max_spawn_value": 48
          },
          {
            "zone_id": "Zone02",
            "collectable_type_spawns": [
              {
                "collectable_type": "co_parrot_01",
                "spawn_value": 75
              },
              {
                "collectable_type": "co_parrot_02",
                "spawn_value": 25
              }
            ],
            "min_spawn_value": 36,
            "max_spawn_value": 42
          },
          {
            "zone_id": "Zone03",
            "collectable_type_spawns": [
              {
                "collectable_type": "co_parrot_01",
                "spawn_value": 75
              },
              {
                "collectable_type": "co_parrot_02",
                "spawn_value": 25
              }
            ],
            "min_spawn_value": 63,
            "max_spawn_value": 69
          }
        ]
      },
      {
        "round_number": "3",
        "zones": [
          {
            "zone_id": "Zone01",
            "collectable_type_spawns": [
              {
                "collectable_type": "co_parrot_01",
                "spawn_value": 60
              },
              {
                "collectable_type": "co_parrot_02",
                "spawn_value": 40
              }
            ],
            "min_spawn_value": 42,
            "max_spawn_value": 48
          },
          {
            "zone_id": "Zone02",
            "collectable_type_spawns": [
              {
                "collectable_type": "co_parrot_01",
                "spawn_value": 60
              },
              {
                "collectable_type": "co_parrot_02",
                "spawn_value": 40
              }
            ],
            "min_spawn_value": 36,
            "max_spawn_value": 42
          },
          {
            "zone_id": "Zone03",
            "collectable_type_spawns": [
              {
                "collectable_type": "co_parrot_01",
                "spawn_value": 60
              },
              {
                "collectable_type": "co_parrot_02",
                "spawn_value": 40
              }
            ],
            "min_spawn_value": 63,
            "max_spawn_value": 69
          }
        ]
      },
      {
        "round_number": "4",
        "zones": [
          {
            "zone_id": "Zone01",
            "collectable_type_spawns": [
              {
                "collectable_type": "co_parrot_01",
                "spawn_value": 60
              },
              {
                "collectable_type": "co_parrot_02",
                "spawn_value": 40
              }
            ],
            "min_spawn_value": 54,
            "max_spawn_value": 60
          },
          {
            "zone_id": "Zone02",
            "collectable_type_spawns": [
              {
                "collectable_type": "co_parrot_01",
                "spawn_value": 60
              },
              {
                "collectable_type": "co_parrot_02",
                "spawn_value": 40
              }
            ],
            "min_spawn_value": 46,
            "max_spawn_value": 52
          },
          {
            "zone_id": "Zone03",
            "collectable_type_spawns": [
              {
                "collectable_type": "co_parrot_01",
                "spawn_value": 60
              },
              {
                "collectable_type": "co_parrot_02",
                "spawn_value": 40
              }
            ],
            "min_spawn_value": 81,
            "max_spawn_value": 87
          }
        ]
      },
      {
        "round_number": "Final",
        "zones": [
          {
            "zone_id": "Zone01",
            "collectable_type_spawns": [
              {
                "collectable_type": "co_parrot_01",
                "spawn_value": 60
              },
              {
                "collectable_type": "co_parrot_02",
                "spawn_value": 40
              }
            ],
            "min_spawn_value": 63,
            "max_spawn_value": 69
          },
          {
            "zone_id": "Zone02",
            "collectable_type_spawns": [
              {
                "collectable_type": "co_parrot_01",
                "spawn_value": 60
              },
              {
                "collectable_type": "co_parrot_02",
                "spawn_value": 40
              }
            ],
            "min_spawn_value": 54,
            "max_spawn_value": 60
          },
          {
            "zone_id": "Zone03",
            "collectable_type_spawns": [
              {
                "collectable_type": "co_parrot_01",
                "spawn_value": 60
              },
              {
                "collectable_type": "co_parrot_02",
                "spawn_value": 40
              }
            ],
            "min_spawn_value": 94,
            "max_spawn_value": 100
          }
        ]
      }
    ],
    "id": "parrot_three_zones"
  },
  {
    "image_override": null,
    "rounds": [
      {
        "round_number": "1",
        "zones": [
          {
            "zone_id": "Zone01",
            "collectable_type_spawns": [
              {
                "collectable_type": "pelican",
                "spawn_value": 100
              }
            ],
            "min_spawn_value": 100,
            "max_spawn_value": 100
          },
          {
            "zone_id": "Zone02",
            "collectable_type_spawns": [
              {
                "collectable_type": "pelican",
                "spawn_value": 0
              }
            ],
            "min_spawn_value": 0,
            "max_spawn_value": 0
          },
          {
            "zone_id": "Zone03",
            "collectable_type_spawns": [
              {
                "collectable_type": "pelican",
                "spawn_value": 0
              }
            ],
            "min_spawn_value": 0,
            "max_spawn_value": 0
          }
        ]
      },
      {
        "round_number": "2",
        "zones": [
          {
            "zone_id": "Zone01",
            "collectable_type_spawns": [
              {
                "collectable_type": "pelican",
                "spawn_value": 100
              }
            ],
            "min_spawn_value": 100,
            "max_spawn_value": 100
          },
          {
            "zone_id": "Zone02",
            "collectable_type_spawns": [
              {
                "collectable_type": "pelican",
                "spawn_value": 0
              }
            ],
            "min_spawn_value": 0,
            "max_spawn_value": 0
          },
          {
            "zone_id": "Zone03",
            "collectable_type_spawns": [
              {
                "collectable_type": "pelican",
                "spawn_value": 0
              }
            ],
            "min_spawn_value": 0,
            "max_spawn_value": 0
          }
        ]
      },
      {
        "round_number": "Final",
        "zones": [
          {
            "zone_id": "Zone01",
            "collectable_type_spawns": [
              {
                "collectable_type": "pelican",
                "spawn_value": 100
              }
            ],
            "min_spawn_value": 100,
            "max_spawn_value": 100
          },
          {
            "zone_id": "Zone02",
            "collectable_type_spawns": [
              {
                "collectable_type": "pelican",
                "spawn_value": 0
              }
            ],
            "min_spawn_value": 0,
            "max_spawn_value": 0
          },
          {
            "zone_id": "Zone03",
            "collectable_type_spawns": [
              {
                "collectable_type": "pelican",
                "spawn_value": 0
              }
            ],
            "min_spawn_value": 0,
            "max_spawn_value": 0
          }
        ]
      }
    ],
    "id": "pelican_one_zone"
  }
]