[
  {
    "dlc_item": {
      "path": "/1620656506/uploads/crown_shards.png",
      "version": "1620656506",
      "filesize": 3310,
      "base": "https://fallguys-assets.gamefuel.info/fallguys-uploads"
    },
    "id": "crown_shards"
  },
  {
    "dlc_item": {
      "path": "/1620730450/uploads/event_background.png",
      "version": "1620730450",
      "filesize": 159325,
      "base": "https://fallguys-assets.gamefuel.info/fallguys-uploads"
    },
    "id": "event_background"
  },
  {
    "dlc_item": {
      "path": "/1620730435/uploads/event_promo_image.png",
      "version": "1620730435",
      "filesize": 652398,
      "base": "https://fallguys-assets.gamefuel.info/fallguys-uploads"
    },
    "id": "event_promo_image"
  },
  {
    "dlc_item": {
      "path": "/1620730564/uploads/event_tooltip.png",
      "version": "1620730564",
      "filesize": 25994,
      "base": "https://fallguys-assets.gamefuel.info/fallguys-uploads"
    },
    "id": "event_tooltip"
  },
  {
    "dlc_item": {
      "path": "/1620730469/uploads/events_currency.png",
      "version": "1620730469",
      "filesize": 11673,
      "base": "https://fallguys-assets.gamefuel.info/fallguys-uploads"
    },
    "id": "events_currency"
  },
  {
    "dlc_item": {
      "path": "/1634298946/uploads/example_image.png",
      "version": "1634298946",
      "filesize": 118515,
      "base": "https://fallguys-assets.gamefuel.info/fallguys-uploads"
    },
    "id": "example_image"
  },
  {
    "dlc_item": {
      "path": "/1628606931/uploads/gems_currency.png",
      "version": "1628606931",
      "filesize": 35548,
      "base": "https://fallguys-assets.gamefuel.info/fallguys-uploads"
    },
    "id": "gems_currency"
  },
  {
    "dlc_item": {
      "path": "/1628783621/uploads/kudos_tile_image_small.png",
      "version": "1628783621",
      "filesize": 295447,
      "base": "https://fallguys-assets.gamefuel.info/fallguys-uploads"
    },
    "id": "kudos_tile_image_small"
  },
  {
    "dlc_item": {
      "path": "/1644418795/uploads/migration_popup_image.png",
      "version": "1644418795",
      "filesize": 180313,
      "base": "https://fallguys-assets.gamefuel.info/fallguys-uploads"
    },
    "id": "migration_popup_image"
  },
  {
    "dlc_item": {
      "path": "/1645027738/uploads/newsfeed_ui_cross_platform_invites.png",
      "version": "1645027738",
      "filesize": 137870,
      "base": "https://fallguys-assets.gamefuel.info/fallguys-uploads"
    },
    "id": "newsfeed_ui_cross_platform_invites"
  },
  {
    "dlc_item": {
      "path": "/1637687764/uploads/newsfeed_ui_eosfeed.png",
      "version": "1637687764",
      "filesize": 500729,
      "base": "https://fallguys-assets.gamefuel.info/fallguys-uploads"
    },
    "id": "newsfeed_ui_eosfeed"
  },
  {
    "dlc_item": {
      "path": "/1643911276/uploads/newsfeed_ui_generic_technical.png",
      "version": "1643911276",
      "filesize": 131690,
      "base": "https://fallguys-assets.gamefuel.info/fallguys-uploads"
    },
    "id": "newsfeed_ui_generic_technical"
  },
  {
    "dlc_item": {
      "path": "/1637687816/uploads/newsfeed_ui_posteosfeed.png",
      "version": "1637687816",
      "filesize": 500729,
      "base": "https://fallguys-assets.gamefuel.info/fallguys-uploads"
    },
    "id": "newsfeed_ui_posteosfeed"
  },
  {
    "dlc_item": {
      "path": "/1647510808/uploads/newsfeed_ui_s6_le_hilaria.png",
      "version": "1647510808",
      "filesize": 230331,
      "base": "https://fallguys-assets.gamefuel.info/fallguys-uploads"
    },
    "id": "newsfeed_ui_s6_le_hilaria"
  },
  {
    "dlc_item": {
      "path": "/1644592921/uploads/show_selector_button_bashers.png",
      "version": "1644592921",
      "filesize": 1072605,
      "base": "https://fallguys-assets.gamefuel.info/fallguys-uploads"
    },
    "id": "show_selector_button_bashers"
  },
  {
    "dlc_item": {
      "path": "/1635248488/uploads/show_selector_oriole.png",
      "version": "1635248488",
      "filesize": 92561,
      "base": "https://fallguys-assets.gamefuel.info/fallguys-uploads"
    },
    "id": "show_selector_oriole"
  },
  {
    "dlc_item": {
      "path": "/1629911156/uploads/show_selector_show_4041.png",
      "version": "1629911156",
      "filesize": 239069,
      "base": "https://fallguys-assets.gamefuel.info/fallguys-uploads"
    },
    "id": "show_selector_show_4041"
  },
  {
    "dlc_item": {
      "path": "/1624267359/uploads/show_selector_show_animals.png",
      "version": "1624267359",
      "filesize": 787087,
      "base": "https://fallguys-assets.gamefuel.info/fallguys-uploads"
    },
    "id": "show_selector_show_animals"
  },
  {
    "dlc_item": {
      "path": "/1648217177/uploads/show_selector_show_aprilstart.png",
      "version": "1648217177",
      "filesize": 574035,
      "base": "https://fallguys-assets.gamefuel.info/fallguys-uploads"
    },
    "id": "show_selector_show_aprilstart"
  },
  {
    "dlc_item": {
      "path": "/1630062224/uploads/show_selector_show_bigshots.png",
      "version": "1630062224",
      "filesize": 612993,
      "base": "https://fallguys-assets.gamefuel.info/fallguys-uploads"
    },
    "id": "show_selector_show_bigshots"
  },
  {
    "dlc_item": {
      "path": "/1630062382/uploads/show_selector_show_bubbles.png",
      "version": "1630062382",
      "filesize": 526722,
      "base": "https://fallguys-assets.gamefuel.info/fallguys-uploads"
    },
    "id": "show_selector_show_bubbles"
  },
  {
    "dlc_item": {
      "path": "/1630062473/uploads/show_selector_show_drumtop.png",
      "version": "1630062473",
      "filesize": 537417,
      "base": "https://fallguys-assets.gamefuel.info/fallguys-uploads"
    },
    "id": "show_selector_show_drumtop"
  },
  {
    "dlc_item": {
      "path": "/1624267505/uploads/show_selector_show_duos.png",
      "version": "1624267505",
      "filesize": 850336,
      "base": "https://fallguys-assets.gamefuel.info/fallguys-uploads"
    },
    "id": "show_selector_show_duos"
  },
  {
    "dlc_item": {
      "path": "/1641838066/uploads/show_selector_show_duos_festival.png",
      "version": "1641838066",
      "filesize": 815524,
      "base": "https://fallguys-assets.gamefuel.info/fallguys-uploads"
    },
    "id": "show_selector_show_duos_festival"
  },
  {
    "dlc_item": {
      "path": "/1635671748/uploads/show_selector_show_end_of_season_01.png",
      "version": "1635671748",
      "filesize": 102459,
      "base": "https://fallguys-assets.gamefuel.info/fallguys-uploads"
    },
    "id": "show_selector_show_end_of_season_01"
  },
  {
    "dlc_item": {
      "path": "/1635671758/uploads/show_selector_show_end_of_season_02.png",
      "version": "1635671758",
      "filesize": 101931,
      "base": "https://fallguys-assets.gamefuel.info/fallguys-uploads"
    },
    "id": "show_selector_show_end_of_season_02"
  },
  {
    "dlc_item": {
      "path": "/1635671765/uploads/show_selector_show_end_of_season_03.png",
      "version": "1635671765",
      "filesize": 98757,
      "base": "https://fallguys-assets.gamefuel.info/fallguys-uploads"
    },
    "id": "show_selector_show_end_of_season_03"
  },
  {
    "dlc_item": {
      "path": "/1635671770/uploads/show_selector_show_end_of_season_04.png",
      "version": "1635671770",
      "filesize": 137756,
      "base": "https://fallguys-assets.gamefuel.info/fallguys-uploads"
    },
    "id": "show_selector_show_end_of_season_04"
  },
  {
    "dlc_item": {
      "path": "/1635671776/uploads/show_selector_show_end_of_season_05.png",
      "version": "1635671776",
      "filesize": 140230,
      "base": "https://fallguys-assets.gamefuel.info/fallguys-uploads"
    },
    "id": "show_selector_show_end_of_season_05"
  },
  {
    "dlc_item": {
      "path": "/1645459350/uploads/show_selector_show_fallballcup.png",
      "version": "1645459350",
      "filesize": 104606,
      "base": "https://fallguys-assets.gamefuel.info/fallguys-uploads"
    },
    "id": "show_selector_show_fallballcup"
  },
  {
    "dlc_item": {
      "path": "/1621509658/uploads/show_selector_show_fanfavourites.png",
      "version": "1621509658",
      "filesize": 983127,
      "base": "https://fallguys-assets.gamefuel.info/fallguys-uploads"
    },
    "id": "show_selector_show_fanfavourites"
  },
  {
    "dlc_item": {
      "path": "/1629911296/uploads/show_selector_show_fruitbasket.png",
      "version": "1629911296",
      "filesize": 246101,
      "base": "https://fallguys-assets.gamefuel.info/fallguys-uploads"
    },
    "id": "show_selector_show_fruitbasket"
  },
  {
    "dlc_item": {
      "path": "/1621509690/uploads/show_selector_show_genericice.png",
      "version": "1621509690",
      "filesize": 895543,
      "base": "https://fallguys-assets.gamefuel.info/fallguys-uploads"
    },
    "id": "show_selector_show_genericice"
  },
  {
    "dlc_item": {
      "path": "/1621509707/uploads/show_selector_show_genericpegwin.png",
      "version": "1621509707",
      "filesize": 860091,
      "base": "https://fallguys-assets.gamefuel.info/fallguys-uploads"
    },
    "id": "show_selector_show_genericpegwin"
  },
  {
    "dlc_item": {
      "path": "/1621509718/uploads/show_selector_show_genericpunch.png",
      "version": "1621509718",
      "filesize": 621273,
      "base": "https://fallguys-assets.gamefuel.info/fallguys-uploads"
    },
    "id": "show_selector_show_genericpunch"
  },
  {
    "dlc_item": {
      "path": "/1621509729/uploads/show_selector_show_genericpusher.png",
      "version": "1621509729",
      "filesize": 1001999,
      "base": "https://fallguys-assets.gamefuel.info/fallguys-uploads"
    },
    "id": "show_selector_show_genericpusher"
  },
  {
    "dlc_item": {
      "path": "/1621509743/uploads/show_selector_show_genericslimeclimb.png",
      "version": "1621509743",
      "filesize": 1049749,
      "base": "https://fallguys-assets.gamefuel.info/fallguys-uploads"
    },
    "id": "show_selector_show_genericslimeclimb"
  },
  {
    "dlc_item": {
      "path": "/1621509405/uploads/show_selector_show_hardmode.png",
      "version": "1621509405",
      "filesize": 408644,
      "base": "https://fallguys-assets.gamefuel.info/fallguys-uploads"
    },
    "id": "show_selector_show_hardmode"
  },
  {
    "dlc_item": {
      "path": "/1629911442/uploads/show_selector_show_hexagonetrials.png",
      "version": "1629911442",
      "filesize": 163340,
      "base": "https://fallguys-assets.gamefuel.info/fallguys-uploads"
    },
    "id": "show_selector_show_hexagonetrials"
  },
  {
    "dlc_item": {
      "path": "/1647452872/uploads/show_selector_show_hilaria.png",
      "version": "1647452872",
      "filesize": 146877,
      "base": "https://fallguys-assets.gamefuel.info/fallguys-uploads"
    },
    "id": "show_selector_show_hilaria"
  },
  {
    "dlc_item": {
      "path": "/1633426924/uploads/show_selector_show_hw_slime_climb.png",
      "version": "1633426924",
      "filesize": 416960,
      "base": "https://fallguys-assets.gamefuel.info/fallguys-uploads"
    },
    "id": "show_selector_show_hw_slime_climb"
  },
  {
    "dlc_item": {
      "path": "/1633426942/uploads/show_selector_show_hw_team_squads.png",
      "version": "1633426942",
      "filesize": 672646,
      "base": "https://fallguys-assets.gamefuel.info/fallguys-uploads"
    },
    "id": "show_selector_show_hw_team_squads"
  },
  {
    "dlc_item": {
      "path": "/1641546701/uploads/show_selector_show_invisibeans.png",
      "version": "1641546701",
      "filesize": 796452,
      "base": "https://fallguys-assets.gamefuel.info/fallguys-uploads"
    },
    "id": "show_selector_show_invisibeans"
  },
  {
    "dlc_item": {
      "path": "/1621509761/uploads/show_selector_show_jumparound.png",
      "version": "1621509761",
      "filesize": 724692,
      "base": "https://fallguys-assets.gamefuel.info/fallguys-uploads"
    },
    "id": "show_selector_show_jumparound"
  },
  {
    "dlc_item": {
      "path": "/1632757509/uploads/show_selector_show_kudosevent_antigrav.png",
      "version": "1632757509",
      "filesize": 216828,
      "base": "https://fallguys-assets.gamefuel.info/fallguys-uploads"
    },
    "id": "show_selector_show_kudosevent_antigrav"
  },
  {
    "dlc_item": {
      "path": "/1632757458/uploads/show_selector_show_kudosevent_fans.png",
      "version": "1632757458",
      "filesize": 209373,
      "base": "https://fallguys-assets.gamefuel.info/fallguys-uploads"
    },
    "id": "show_selector_show_kudosevent_fans"
  },
  {
    "dlc_item": {
      "path": "/1632757415/uploads/show_selector_show_kudosevent_jump.png",
      "version": "1632757415",
      "filesize": 183065,
      "base": "https://fallguys-assets.gamefuel.info/fallguys-uploads"
    },
    "id": "show_selector_show_kudosevent_jump"
  },
  {
    "dlc_item": {
      "path": "/1632757524/uploads/show_selector_show_kudosevent_pillars.png",
      "version": "1632757524",
      "filesize": 213135,
      "base": "https://fallguys-assets.gamefuel.info/fallguys-uploads"
    },
    "id": "show_selector_show_kudosevent_pillars"
  },
  {
    "dlc_item": {
      "path": "/1632757439/uploads/show_selector_show_kudosevent_turnable.png",
      "version": "1632757439",
      "filesize": 205155,
      "base": "https://fallguys-assets.gamefuel.info/fallguys-uploads"
    },
    "id": "show_selector_show_kudosevent_turnable"
  },
  {
    "dlc_item": {
      "path": "/1629458228/uploads/show_selector_show_lilyleaperslimbo.png",
      "version": "1629458228",
      "filesize": 1095528,
      "base": "https://fallguys-assets.gamefuel.info/fallguys-uploads"
    },
    "id": "show_selector_show_lilyleaperslimbo"
  },
  {
    "dlc_item": {
      "path": "/1629911564/uploads/show_selector_show_mainshow.png",
      "version": "1629911564",
      "filesize": 177475,
      "base": "https://fallguys-assets.gamefuel.info/fallguys-uploads"
    },
    "id": "show_selector_show_mainshow"
  },
  {
    "dlc_item": {
      "path": "/1621509436/uploads/show_selector_show_medievalmixup.png",
      "version": "1621509436",
      "filesize": 371651,
      "base": "https://fallguys-assets.gamefuel.info/fallguys-uploads"
    },
    "id": "show_selector_show_medievalmixup"
  },
  {
    "dlc_item": {
      "path": "/1629292196/uploads/show_selector_show_midautumn.png",
      "version": "1629292196",
      "filesize": 1315491,
      "base": "https://fallguys-assets.gamefuel.info/fallguys-uploads"
    },
    "id": "show_selector_show_midautumn"
  },
  {
    "dlc_item": {
      "path": "/1621509772/uploads/show_selector_show_mixitup.png",
      "version": "1621509772",
      "filesize": 977787,
      "base": "https://fallguys-assets.gamefuel.info/fallguys-uploads"
    },
    "id": "show_selector_show_mixitup"
  },
  {
    "dlc_item": {
      "path": "/1637928633/uploads/show_selector_show_newyears6.png",
      "version": "1637928633",
      "filesize": 1030615,
      "base": "https://fallguys-assets.gamefuel.info/fallguys-uploads"
    },
    "id": "show_selector_show_newyears6"
  },
  {
    "dlc_item": {
      "path": "/1630062217/uploads/show_selector_show_ninja.png",
      "version": "1630062217",
      "filesize": 318081,
      "base": "https://fallguys-assets.gamefuel.info/fallguys-uploads"
    },
    "id": "show_selector_show_ninja"
  },
  {
    "dlc_item": {
      "path": "/1621509982/uploads/show_selector_show_northernlion.png",
      "version": "1621509982",
      "filesize": 211676,
      "base": "https://fallguys-assets.gamefuel.info/fallguys-uploads"
    },
    "id": "show_selector_show_northernlion"
  },
  {
    "dlc_item": {
      "path": "/1638361587/uploads/show_selector_show_only_finals.png",
      "version": "1638361587",
      "filesize": 169449,
      "base": "https://fallguys-assets.gamefuel.info/fallguys-uploads"
    },
    "id": "show_selector_show_only_finals"
  },
  {
    "dlc_item": {
      "path": "/1624267483/uploads/show_selector_show_party.png",
      "version": "1624267483",
      "filesize": 945299,
      "base": "https://fallguys-assets.gamefuel.info/fallguys-uploads"
    },
    "id": "show_selector_show_party"
  },
  {
    "dlc_item": {
      "path": "/1629911366/uploads/show_selector_show_racelevels.png",
      "version": "1629911366",
      "filesize": 206411,
      "base": "https://fallguys-assets.gamefuel.info/fallguys-uploads"
    },
    "id": "show_selector_show_racelevels"
  },
  {
    "dlc_item": {
      "path": "/1621509784/uploads/show_selector_show_rollcall.png",
      "version": "1621509784",
      "filesize": 940251,
      "base": "https://fallguys-assets.gamefuel.info/fallguys-uploads"
    },
    "id": "show_selector_show_rollcall"
  },
  {
    "dlc_item": {
      "path": "/1630062343/uploads/show_selector_show_s401.png",
      "version": "1630062343",
      "filesize": 442636,
      "base": "https://fallguys-assets.gamefuel.info/fallguys-uploads"
    },
    "id": "show_selector_show_s401"
  },
  {
    "dlc_item": {
      "path": "/1621510551/uploads/show_selector_show_s402.png",
      "version": "1621510551",
      "filesize": 994611,
      "base": "https://fallguys-assets.gamefuel.info/fallguys-uploads"
    },
    "id": "show_selector_show_s402"
  },
  {
    "dlc_item": {
      "path": "/1621510559/uploads/show_selector_show_s403.png",
      "version": "1621510559",
      "filesize": 811597,
      "base": "https://fallguys-assets.gamefuel.info/fallguys-uploads"
    },
    "id": "show_selector_show_s403"
  },
  {
    "dlc_item": {
      "path": "/1621510566/uploads/show_selector_show_s404.png",
      "version": "1621510566",
      "filesize": 949709,
      "base": "https://fallguys-assets.gamefuel.info/fallguys-uploads"
    },
    "id": "show_selector_show_s404"
  },
  {
    "dlc_item": {
      "path": "/1621510574/uploads/show_selector_show_s405.png",
      "version": "1621510574",
      "filesize": 1034010,
      "base": "https://fallguys-assets.gamefuel.info/fallguys-uploads"
    },
    "id": "show_selector_show_s405"
  },
  {
    "dlc_item": {
      "path": "/1630062336/uploads/show_selector_show_s406.png",
      "version": "1630062336",
      "filesize": 523722,
      "base": "https://fallguys-assets.gamefuel.info/fallguys-uploads"
    },
    "id": "show_selector_show_s406"
  },
  {
    "dlc_item": {
      "path": "/1621510590/uploads/show_selector_show_s407.png",
      "version": "1621510590",
      "filesize": 895900,
      "base": "https://fallguys-assets.gamefuel.info/fallguys-uploads"
    },
    "id": "show_selector_show_s407"
  },
  {
    "dlc_item": {
      "path": "/1630062479/uploads/show_selector_show_s408.png",
      "version": "1630062479",
      "filesize": 406755,
      "base": "https://fallguys-assets.gamefuel.info/fallguys-uploads"
    },
    "id": "show_selector_show_s408"
  },
  {
    "dlc_item": {
      "path": "/1621510603/uploads/show_selector_show_s409.png",
      "version": "1621510603",
      "filesize": 691524,
      "base": "https://fallguys-assets.gamefuel.info/fallguys-uploads"
    },
    "id": "show_selector_show_s409"
  },
  {
    "dlc_item": {
      "path": "/1621510615/uploads/show_selector_show_s410.png",
      "version": "1621510615",
      "filesize": 1012469,
      "base": "https://fallguys-assets.gamefuel.info/fallguys-uploads"
    },
    "id": "show_selector_show_s410"
  },
  {
    "dlc_item": {
      "path": "/1621510623/uploads/show_selector_show_s411.png",
      "version": "1621510623",
      "filesize": 836348,
      "base": "https://fallguys-assets.gamefuel.info/fallguys-uploads"
    },
    "id": "show_selector_show_s411"
  },
  {
    "dlc_item": {
      "path": "/1621510655/uploads/show_selector_show_s4501.png",
      "version": "1621510655",
      "filesize": 1022023,
      "base": "https://fallguys-assets.gamefuel.info/fallguys-uploads"
    },
    "id": "show_selector_show_s4501"
  },
  {
    "dlc_item": {
      "path": "/1630062400/uploads/show_selector_show_s4502.png",
      "version": "1630062400",
      "filesize": 429600,
      "base": "https://fallguys-assets.gamefuel.info/fallguys-uploads"
    },
    "id": "show_selector_show_s4502"
  },
  {
    "dlc_item": {
      "path": "/1621510666/uploads/show_selector_show_s4503.png",
      "version": "1621510666",
      "filesize": 800564,
      "base": "https://fallguys-assets.gamefuel.info/fallguys-uploads"
    },
    "id": "show_selector_show_s4503"
  },
  {
    "dlc_item": {
      "path": "/1621510672/uploads/show_selector_show_s4504.png",
      "version": "1621510672",
      "filesize": 859071,
      "base": "https://fallguys-assets.gamefuel.info/fallguys-uploads"
    },
    "id": "show_selector_show_s4504"
  },
  {
    "dlc_item": {
      "path": "/1621510678/uploads/show_selector_show_s4505.png",
      "version": "1621510678",
      "filesize": 935620,
      "base": "https://fallguys-assets.gamefuel.info/fallguys-uploads"
    },
    "id": "show_selector_show_s4505"
  },
  {
    "dlc_item": {
      "path": "/1621510685/uploads/show_selector_show_s4506.png",
      "version": "1621510685",
      "filesize": 711259,
      "base": "https://fallguys-assets.gamefuel.info/fallguys-uploads"
    },
    "id": "show_selector_show_s4506"
  },
  {
    "dlc_item": {
      "path": "/1630062301/uploads/show_selector_show_s4507.png",
      "version": "1630062301",
      "filesize": 452144,
      "base": "https://fallguys-assets.gamefuel.info/fallguys-uploads"
    },
    "id": "show_selector_show_s4507"
  },
  {
    "dlc_item": {
      "path": "/1630062295/uploads/show_selector_show_s4508.png",
      "version": "1630062295",
      "filesize": 452590,
      "base": "https://fallguys-assets.gamefuel.info/fallguys-uploads"
    },
    "id": "show_selector_show_s4508"
  },
  {
    "dlc_item": {
      "path": "/1630062394/uploads/show_selector_show_s4509.png",
      "version": "1630062394",
      "filesize": 387454,
      "base": "https://fallguys-assets.gamefuel.info/fallguys-uploads"
    },
    "id": "show_selector_show_s4509"
  },
  {
    "dlc_item": {
      "path": "/1621510717/uploads/show_selector_show_s4510.png",
      "version": "1621510717",
      "filesize": 512585,
      "base": "https://fallguys-assets.gamefuel.info/fallguys-uploads"
    },
    "id": "show_selector_show_s4510"
  },
  {
    "dlc_item": {
      "path": "/1635867302/uploads/show_selector_show_s6launch.png",
      "version": "1635867302",
      "filesize": 131627,
      "base": "https://fallguys-assets.gamefuel.info/fallguys-uploads"
    },
    "id": "show_selector_show_s6launch"
  },
  {
    "dlc_item": {
      "path": "/1630062209/uploads/show_selector_show_season3.png",
      "version": "1630062209",
      "filesize": 201230,
      "base": "https://fallguys-assets.gamefuel.info/fallguys-uploads"
    },
    "id": "show_selector_show_season3"
  },
  {
    "dlc_item": {
      "path": "/1624266644/uploads/show_selector_show_season5.png",
      "version": "1624266644",
      "filesize": 1035306,
      "base": "https://fallguys-assets.gamefuel.info/fallguys-uploads"
    },
    "id": "show_selector_show_season5"
  },
  {
    "dlc_item": {
      "path": "/1621509803/uploads/show_selector_show_slamdunk.png",
      "version": "1621509803",
      "filesize": 934191,
      "base": "https://fallguys-assets.gamefuel.info/fallguys-uploads"
    },
    "id": "show_selector_show_slamdunk"
  },
  {
    "dlc_item": {
      "path": "/1621509814/uploads/show_selector_show_slimetrials.png",
      "version": "1621509814",
      "filesize": 834660,
      "base": "https://fallguys-assets.gamefuel.info/fallguys-uploads"
    },
    "id": "show_selector_show_slimetrials"
  },
  {
    "dlc_item": {
      "path": "/1624267460/uploads/show_selector_show_sports.png",
      "version": "1624267460",
      "filesize": 907121,
      "base": "https://fallguys-assets.gamefuel.info/fallguys-uploads"
    },
    "id": "show_selector_show_sports"
  },
  {
    "dlc_item": {
      "path": "/1638294156/uploads/show_selector_show_sports_suddendeath.png",
      "version": "1638294156",
      "filesize": 151151,
      "base": "https://fallguys-assets.gamefuel.info/fallguys-uploads"
    },
    "id": "show_selector_show_sports_suddendeath"
  },
  {
    "dlc_item": {
      "path": "/1630062459/uploads/show_selector_show_squadshows.png",
      "version": "1630062459",
      "filesize": 421397,
      "base": "https://fallguys-assets.gamefuel.info/fallguys-uploads"
    },
    "id": "show_selector_show_squadshows"
  },
  {
    "dlc_item": {
      "path": "/1648714792/uploads/show_selector_show_stars_02.png",
      "version": "1648714792",
      "filesize": 833526,
      "base": "https://fallguys-assets.gamefuel.info/fallguys-uploads"
    },
    "id": "show_selector_show_stars_02"
  },
  {
    "dlc_item": {
      "path": "/1629911673/uploads/show_selector_show_survivallevels.png",
      "version": "1629911673",
      "filesize": 74867,
      "base": "https://fallguys-assets.gamefuel.info/fallguys-uploads"
    },
    "id": "show_selector_show_survivallevels"
  },
  {
    "dlc_item": {
      "path": "/1621509921/uploads/show_selector_show_tailtag.png",
      "version": "1621509921",
      "filesize": 816830,
      "base": "https://fallguys-assets.gamefuel.info/fallguys-uploads"
    },
    "id": "show_selector_show_tailtag"
  },
  {
    "dlc_item": {
      "path": "/1641463670/uploads/show_selector_show_thinice.png",
      "version": "1641463670",
      "filesize": 74866,
      "base": "https://fallguys-assets.gamefuel.info/fallguys-uploads"
    },
    "id": "show_selector_show_thinice"
  },
  {
    "dlc_item": {
      "path": "/1624267411/uploads/show_selector_show_tiptoe.png",
      "version": "1624267411",
      "filesize": 962389,
      "base": "https://fallguys-assets.gamefuel.info/fallguys-uploads"
    },
    "id": "show_selector_show_tiptoe"
  },
  {
    "dlc_item": {
      "path": "/1624635440/uploads/show_selector_show_trios.png",
      "version": "1624635440",
      "filesize": 703288,
      "base": "https://fallguys-assets.gamefuel.info/fallguys-uploads"
    },
    "id": "show_selector_show_trios"
  },
  {
    "dlc_item": {
      "path": "/1621509965/uploads/show_selector_show_twitchrivals.png",
      "version": "1621509965",
      "filesize": 368505,
      "base": "https://fallguys-assets.gamefuel.info/fallguys-uploads"
    },
    "id": "show_selector_show_twitchrivals"
  },
  {
    "dlc_item": {
      "path": "/1636988932/uploads/show_selector_show_vulture.png",
      "version": "1636988932",
      "filesize": 760356,
      "base": "https://fallguys-assets.gamefuel.info/fallguys-uploads"
    },
    "id": "show_selector_show_vulture"
  },
  {
    "dlc_item": {
      "path": "/1638294167/uploads/show_selector_show_xtreme_squads.png",
      "version": "1638294167",
      "filesize": 208692,
      "base": "https://fallguys-assets.gamefuel.info/fallguys-uploads"
    },
    "id": "show_selector_show_xtreme_squads"
  },
  {
    "dlc_item": {
      "path": "/1621510007/uploads/show_selector_show_yeetustour.png",
      "version": "1621510007",
      "filesize": 212131,
      "base": "https://fallguys-assets.gamefuel.info/fallguys-uploads"
    },
    "id": "show_selector_show_yeetustour"
  },
  {
    "dlc_item": {
      "path": "/1628784236/uploads/temp-primos_small_tile.png",
      "version": "1628784236",
      "filesize": 252928,
      "base": "https://fallguys-assets.gamefuel.info/fallguys-uploads"
    },
    "id": "temp-primos_small_tile"
  },
  {
    "dlc_item": {
      "path": "/1628785975/uploads/temp_placeholder_seasonpass.png",
      "version": "1628785975",
      "filesize": 855958,
      "base": "https://fallguys-assets.gamefuel.info/fallguys-uploads"
    },
    "id": "temp_placeholder_seasonpass"
  },
  {
    "dlc_item": {
      "path": "/1628785168/uploads/temp_placeholder_sonic_2x2.png",
      "version": "1628785168",
      "filesize": 795281,
      "base": "https://fallguys-assets.gamefuel.info/fallguys-uploads"
    },
    "id": "temp_placeholder_sonic_2x2"
  },
  {
    "dlc_item": {
      "path": "/1632912602/uploads/test_costumeset_bigfoot_1x2.png",
      "version": "1632912602",
      "filesize": 98178,
      "base": "https://fallguys-assets.gamefuel.info/fallguys-uploads"
    },
    "id": "test_costumeset_bigfoot_1x2"
  },
  {
    "dlc_item": {
      "path": "/1632912469/uploads/test_costumeset_yeti_1x2.png",
      "version": "1632912469",
      "filesize": 129475,
      "base": "https://fallguys-assets.gamefuel.info/fallguys-uploads"
    },
    "id": "test_costumeset_yeti_1x2"
  },
  {
    "dlc_item": {
      "path": "/1632842434/uploads/test_doomslayer_costumeset.png",
      "version": "1632842434",
      "filesize": 110026,
      "base": "https://fallguys-assets.gamefuel.info/fallguys-uploads"
    },
    "id": "test_doomslayer_costumeset"
  },
  {
    "dlc_item": {
      "path": "/1629474716/uploads/test_only_1x2_costumeset_cactus.png",
      "version": "1629474716",
      "filesize": 113026,
      "base": "https://fallguys-assets.gamefuel.info/fallguys-uploads"
    },
    "id": "test_only_1x2_costumeset_cactus"
  },
  {
    "dlc_item": {
      "path": "/1629474701/uploads/test_only_1x2_costumeset_fluffball.png",
      "version": "1629474701",
      "filesize": 127693,
      "base": "https://fallguys-assets.gamefuel.info/fallguys-uploads"
    },
    "id": "test_only_1x2_costumeset_fluffball"
  },
  {
    "dlc_item": {
      "path": "/1629474684/uploads/test_only_1x2_costumeset_oliver.png",
      "version": "1629474684",
      "filesize": 117443,
      "base": "https://fallguys-assets.gamefuel.info/fallguys-uploads"
    },
    "id": "test_only_1x2_costumeset_oliver"
  },
  {
    "dlc_item": {
      "path": "/1629474667/uploads/test_only_1x2_costumeset_quackers.png",
      "version": "1629474667",
      "filesize": 134707,
      "base": "https://fallguys-assets.gamefuel.info/fallguys-uploads"
    },
    "id": "test_only_1x2_costumeset_quackers"
  },
  {
    "dlc_item": {
      "path": "/1629474648/uploads/test_only_1x2_costumeset_rainbow.png",
      "version": "1629474648",
      "filesize": 120965,
      "base": "https://fallguys-assets.gamefuel.info/fallguys-uploads"
    },
    "id": "test_only_1x2_costumeset_rainbow"
  },
  {
    "dlc_item": {
      "path": "/1629474632/uploads/test_only_1x2_costumeset_sparkle-whal.png",
      "version": "1629474632",
      "filesize": 115435,
      "base": "https://fallguys-assets.gamefuel.info/fallguys-uploads"
    },
    "id": "test_only_1x2_costumeset_sparkle-whal"
  },
  {
    "dlc_item": {
      "path": "/1629474605/uploads/test_only_1x2_costumeset_witch.png",
      "version": "1629474605",
      "filesize": 125052,
      "base": "https://fallguys-assets.gamefuel.info/fallguys-uploads"
    },
    "id": "test_only_1x2_costumeset_witch"
  },
  {
    "dlc_item": {
      "path": "/1629198646/uploads/test_only_seasonpass_bundle_popup.png",
      "version": "1629198646",
      "filesize": 2033876,
      "base": "https://fallguys-assets.gamefuel.info/fallguys-uploads"
    },
    "id": "test_only_seasonpass_bundle_popup"
  },
  {
    "dlc_item": {
      "path": "/1624549614/uploads/ui-icon-dove01-token.png",
      "version": "1624549614",
      "filesize": 12714,
      "base": "https://fallguys-assets.gamefuel.info/fallguys-uploads"
    },
    "id": "ui-icon-dove01-token"
  },
  {
    "dlc_item": {
      "path": "/1624549664/uploads/ui-icon-dove02-token.png",
      "version": "1624549664",
      "filesize": 11712,
      "base": "https://fallguys-assets.gamefuel.info/fallguys-uploads"
    },
    "id": "ui-icon-dove02-token"
  },
  {
    "dlc_item": {
      "path": "/1624549730/uploads/ui-icon-generic-token.png",
      "version": "1624549730",
      "filesize": 12631,
      "base": "https://fallguys-assets.gamefuel.info/fallguys-uploads"
    },
    "id": "ui-icon-generic-token"
  },
  {
    "dlc_item": {
      "path": "/1633334765/uploads/ui-icon-halloween-token.png",
      "version": "1633334765",
      "filesize": 27632,
      "base": "https://fallguys-assets.gamefuel.info/fallguys-uploads"
    },
    "id": "ui-icon-halloween-token"
  },
  {
    "dlc_item": {
      "path": "/1648563066/uploads/ui-icon-s6-stars-event.png",
      "version": "1648563066",
      "filesize": 39168,
      "base": "https://fallguys-assets.gamefuel.info/fallguys-uploads"
    },
    "id": "ui-icon-s6-stars-event"
  },
  {
    "dlc_item": {
      "path": "/1629276512/uploads/ui-icon-tucan-token.png",
      "version": "1629276512",
      "filesize": 15055,
      "base": "https://fallguys-assets.gamefuel.info/fallguys-uploads"
    },
    "id": "ui-icon-tucan-token"
  },
  {
    "dlc_item": {
      "path": "/1624549690/uploads/ui-liveevents-crownladder-tooltip.png",
      "version": "1624549690",
      "filesize": 25123,
      "base": "https://fallguys-assets.gamefuel.info/fallguys-uploads"
    },
    "id": "ui-liveevents-crownladder-tooltip"
  },
  {
    "dlc_item": {
      "path": "/1626358823/uploads/ui-liveevents-dove01-bg.png",
      "version": "1626358823",
      "filesize": 1343057,
      "base": "https://fallguys-assets.gamefuel.info/fallguys-uploads"
    },
    "id": "ui-liveevents-dove01-bg"
  },
  {
    "dlc_item": {
      "path": "/1624549602/uploads/ui-liveevents-dove01-costume.png",
      "version": "1624549602",
      "filesize": 750027,
      "base": "https://fallguys-assets.gamefuel.info/fallguys-uploads"
    },
    "id": "ui-liveevents-dove01-costume"
  },
  {
    "dlc_item": {
      "path": "/1624549574/uploads/ui-liveevents-dove01-tooltip.png",
      "version": "1624549574",
      "filesize": 40016,
      "base": "https://fallguys-assets.gamefuel.info/fallguys-uploads"
    },
    "id": "ui-liveevents-dove01-tooltip"
  },
  {
    "dlc_item": {
      "path": "/1624549645/uploads/ui-liveevents-dove02-bg.png",
      "version": "1624549645",
      "filesize": 1173229,
      "base": "https://fallguys-assets.gamefuel.info/fallguys-uploads"
    },
    "id": "ui-liveevents-dove02-bg"
  },
  {
    "dlc_item": {
      "path": "/1624549655/uploads/ui-liveevents-dove02-costume.png",
      "version": "1624549655",
      "filesize": 731494,
      "base": "https://fallguys-assets.gamefuel.info/fallguys-uploads"
    },
    "id": "ui-liveevents-dove02-costume"
  },
  {
    "dlc_item": {
      "path": "/1624549637/uploads/ui-liveevents-dove02-tooltip.png",
      "version": "1624549637",
      "filesize": 39238,
      "base": "https://fallguys-assets.gamefuel.info/fallguys-uploads"
    },
    "id": "ui-liveevents-dove02-tooltip"
  },
  {
    "dlc_item": {
      "path": "/1624549753/uploads/ui-liveevents-generic-bg-blue.png",
      "version": "1624549753",
      "filesize": 214284,
      "base": "https://fallguys-assets.gamefuel.info/fallguys-uploads"
    },
    "id": "ui-liveevents-generic-bg-blue"
  },
  {
    "dlc_item": {
      "path": "/1624549759/uploads/ui-liveevents-generic-bg-orange.png",
      "version": "1624549759",
      "filesize": 180901,
      "base": "https://fallguys-assets.gamefuel.info/fallguys-uploads"
    },
    "id": "ui-liveevents-generic-bg-orange"
  },
  {
    "dlc_item": {
      "path": "/1624549764/uploads/ui-liveevents-generic-bg-pink.png",
      "version": "1624549764",
      "filesize": 159325,
      "base": "https://fallguys-assets.gamefuel.info/fallguys-uploads"
    },
    "id": "ui-liveevents-generic-bg-pink"
  },
  {
    "dlc_item": {
      "path": "/1624549770/uploads/ui-liveevents-generic-bg-purple.png",
      "version": "1624549770",
      "filesize": 164897,
      "base": "https://fallguys-assets.gamefuel.info/fallguys-uploads"
    },
    "id": "ui-liveevents-generic-bg-purple"
  },
  {
    "dlc_item": {
      "path": "/1624549701/uploads/ui-liveevents-generic-bg-yellow.png",
      "version": "1624549701",
      "filesize": 129786,
      "base": "https://fallguys-assets.gamefuel.info/fallguys-uploads"
    },
    "id": "ui-liveevents-generic-bg-yellow"
  },
  {
    "dlc_item": {
      "path": "/1620838519/uploads/ui-liveevents-generic-costume-placeholder.png",
      "version": "1620838519",
      "filesize": 652398,
      "base": "https://fallguys-assets.gamefuel.info/fallguys-uploads"
    },
    "id": "ui-liveevents-generic-costume-placeholder"
  },
  {
    "dlc_item": {
      "path": "/1620838542/uploads/ui-liveevents-generic-tooltip-placeholder.png",
      "version": "1620838542",
      "filesize": 25994,
      "base": "https://fallguys-assets.gamefuel.info/fallguys-uploads"
    },
    "id": "ui-liveevents-generic-tooltip-placeholder"
  },
  {
    "dlc_item": {
      "path": "/1624549721/uploads/ui-liveevents-goldenhotdog-costume.png",
      "version": "1624549721",
      "filesize": 766795,
      "base": "https://fallguys-assets.gamefuel.info/fallguys-uploads"
    },
    "id": "ui-liveevents-goldenhotdog-costume"
  },
  {
    "dlc_item": {
      "path": "/1633334732/uploads/ui-liveevents-halloween-bg.png",
      "version": "1633334732",
      "filesize": 118574,
      "base": "https://fallguys-assets.gamefuel.info/fallguys-uploads"
    },
    "id": "ui-liveevents-halloween-bg"
  },
  {
    "dlc_item": {
      "path": "/1633334748/uploads/ui-liveevents-halloween-costume.png",
      "version": "1633334748",
      "filesize": 817877,
      "base": "https://fallguys-assets.gamefuel.info/fallguys-uploads"
    },
    "id": "ui-liveevents-halloween-costume"
  },
  {
    "dlc_item": {
      "path": "/1633334708/uploads/ui-liveevents-halloween-tooltip.png",
      "version": "1633334708",
      "filesize": 32761,
      "base": "https://fallguys-assets.gamefuel.info/fallguys-uploads"
    },
    "id": "ui-liveevents-halloween-tooltip"
  },
  {
    "dlc_item": {
      "path": "/1647337590/uploads/ui-liveevents-hilaria-tooltip.png",
      "version": "1647337590",
      "filesize": 20406,
      "base": "https://fallguys-assets.gamefuel.info/fallguys-uploads"
    },
    "id": "ui-liveevents-hilaria-tooltip"
  },
  {
    "dlc_item": {
      "path": "/1629278256/uploads/ui-liveevents-midautumn-bg.png",
      "version": "1629278256",
      "filesize": 119926,
      "base": "https://fallguys-assets.gamefuel.info/fallguys-uploads"
    },
    "id": "ui-liveevents-midautumn-bg"
  },
  {
    "dlc_item": {
      "path": "/1629278272/uploads/ui-liveevents-midautumn-costume.png",
      "version": "1629278272",
      "filesize": 986836,
      "base": "https://fallguys-assets.gamefuel.info/fallguys-uploads"
    },
    "id": "ui-liveevents-midautumn-costume"
  },
  {
    "dlc_item": {
      "path": "/1629278283/uploads/ui-liveevents-midautumn-token.png",
      "version": "1629278283",
      "filesize": 15978,
      "base": "https://fallguys-assets.gamefuel.info/fallguys-uploads"
    },
    "id": "ui-liveevents-midautumn-token"
  },
  {
    "dlc_item": {
      "path": "/1629278306/uploads/ui-liveevents-midautumn-tooltip.png",
      "version": "1629278306",
      "filesize": 33194,
      "base": "https://fallguys-assets.gamefuel.info/fallguys-uploads"
    },
    "id": "ui-liveevents-midautumn-tooltip"
  },
  {
    "dlc_item": {
      "path": "/1638187124/uploads/ui-liveevents-newyears6-bg.png",
      "version": "1638187124",
      "filesize": 342666,
      "base": "https://fallguys-assets.gamefuel.info/fallguys-uploads"
    },
    "id": "ui-liveevents-newyears6-bg"
  },
  {
    "dlc_item": {
      "path": "/1638186928/uploads/ui-liveevents-newyears6-costume.png",
      "version": "1638186928",
      "filesize": 621470,
      "base": "https://fallguys-assets.gamefuel.info/fallguys-uploads"
    },
    "id": "ui-liveevents-newyears6-costume"
  },
  {
    "dlc_item": {
      "path": "/1638187257/uploads/ui-liveevents-newyears6-token.png",
      "version": "1638187257",
      "filesize": 12130,
      "base": "https://fallguys-assets.gamefuel.info/fallguys-uploads"
    },
    "id": "ui-liveevents-newyears6-token"
  },
  {
    "dlc_item": {
      "path": "/1638187266/uploads/ui-liveevents-newyears6-tooltip.png",
      "version": "1638187266",
      "filesize": 43052,
      "base": "https://fallguys-assets.gamefuel.info/fallguys-uploads"
    },
    "id": "ui-liveevents-newyears6-tooltip"
  },
  {
    "dlc_item": {
      "path": "/1635867183/uploads/ui-liveevents-s6launch-bg.png",
      "version": "1635867183",
      "filesize": 158000,
      "base": "https://fallguys-assets.gamefuel.info/fallguys-uploads"
    },
    "id": "ui-liveevents-s6launch-bg"
  },
  {
    "dlc_item": {
      "path": "/1635867161/uploads/ui-liveevents-s6launch-costume.png",
      "version": "1635867161",
      "filesize": 861197,
      "base": "https://fallguys-assets.gamefuel.info/fallguys-uploads"
    },
    "id": "ui-liveevents-s6launch-costume"
  },
  {
    "dlc_item": {
      "path": "/1635867213/uploads/ui-liveevents-s6launch-token.png",
      "version": "1635867213",
      "filesize": 31103,
      "base": "https://fallguys-assets.gamefuel.info/fallguys-uploads"
    },
    "id": "ui-liveevents-s6launch-token"
  },
  {
    "dlc_item": {
      "path": "/1635867231/uploads/ui-liveevents-s6launch-tooltip.png",
      "version": "1635867231",
      "filesize": 41998,
      "base": "https://fallguys-assets.gamefuel.info/fallguys-uploads"
    },
    "id": "ui-liveevents-s6launch-tooltip"
  },
  {
    "dlc_item": {
      "path": "/1648563047/uploads/ui-liveevents-stars-01-costume.png",
      "version": "1648563047",
      "filesize": 558682,
      "base": "https://fallguys-assets.gamefuel.info/fallguys-uploads"
    },
    "id": "ui-liveevents-stars-01-costume"
  },
  {
    "dlc_item": {
      "path": "/1647364200/uploads/ui-liveevents-star-02-costume.png",
      "version": "1647364200",
      "filesize": 673024,
      "base": "https://fallguys-assets.gamefuel.info/fallguys-uploads"
    },
    "id": "ui-liveevents-stars-02-costume"
  },
  {
    "dlc_item": {
      "path": "/1649251345/uploads/ui-liveevents-stars-bg-2.png",
      "version": "1649251345",
      "filesize": 450881,
      "base": "https://fallguys-assets.gamefuel.info/fallguys-uploads"
    },
    "id": "ui-liveevents-stars-bg-2"
  },
  {
    "dlc_item": {
      "path": "/1648563056/uploads/ui-liveevents-stars-bg.png",
      "version": "1648563056",
      "filesize": 696673,
      "base": "https://fallguys-assets.gamefuel.info/fallguys-uploads"
    },
    "id": "ui-liveevents-stars-bg"
  },
  {
    "dlc_item": {
      "path": "/1648217061/uploads/ui-liveevents-stars1-tooltip.png",
      "version": "1648217061",
      "filesize": 61909,
      "base": "https://fallguys-assets.gamefuel.info/fallguys-uploads"
    },
    "id": "ui-liveevents-stars1-tooltip"
  },
  {
    "dlc_item": {
      "path": "/1649251361/uploads/ui-liveevents-stars2-costume.png",
      "version": "1649251361",
      "filesize": 633040,
      "base": "https://fallguys-assets.gamefuel.info/fallguys-uploads"
    },
    "id": "ui-liveevents-stars2-costume"
  },
  {
    "dlc_item": {
      "path": "/1648727578/uploads/ui-liveevents-stars2-tooltip.png",
      "version": "1648727578",
      "filesize": 51799,
      "base": "https://fallguys-assets.gamefuel.info/fallguys-uploads"
    },
    "id": "ui-liveevents-stars2-tooltip"
  },
  {
    "dlc_item": {
      "path": "/1647337709/uploads/ui-liveevents-tanager02-costume.png",
      "version": "1647337709",
      "filesize": 408347,
      "base": "https://fallguys-assets.gamefuel.info/fallguys-uploads"
    },
    "id": "ui-liveevents-tanager02-costume"
  },
  {
    "dlc_item": {
      "path": "/1629276500/uploads/ui-liveevents-tucan-bg.png",
      "version": "1629276500",
      "filesize": 162244,
      "base": "https://fallguys-assets.gamefuel.info/fallguys-uploads"
    },
    "id": "ui-liveevents-tucan-bg"
  },
  {
    "dlc_item": {
      "path": "/1629276507/uploads/ui-liveevents-tucan-costume.png",
      "version": "1629276507",
      "filesize": 625922,
      "base": "https://fallguys-assets.gamefuel.info/fallguys-uploads"
    },
    "id": "ui-liveevents-tucan-costume"
  },
  {
    "dlc_item": {
      "path": "/1629276492/uploads/ui-liveevents-tucan-tooltip.png",
      "version": "1629276492",
      "filesize": 35223,
      "base": "https://fallguys-assets.gamefuel.info/fallguys-uploads"
    },
    "id": "ui-liveevents-tucan-tooltip"
  },
  {
    "dlc_item": {
      "path": "/1636639802/uploads/ui-liveevents-vulture-bg.png",
      "version": "1636639802",
      "filesize": 266030,
      "base": "https://fallguys-assets.gamefuel.info/fallguys-uploads"
    },
    "id": "ui-liveevents-vulture-bg"
  },
  {
    "dlc_item": {
      "path": "/1636639833/uploads/ui-liveevents-vulture-costume.png",
      "version": "1636639833",
      "filesize": 688894,
      "base": "https://fallguys-assets.gamefuel.info/fallguys-uploads"
    },
    "id": "ui-liveevents-vulture-costume"
  },
  {
    "dlc_item": {
      "path": "/1636639852/uploads/ui-liveevents-vulture-token.png",
      "version": "1636639852",
      "filesize": 23165,
      "base": "https://fallguys-assets.gamefuel.info/fallguys-uploads"
    },
    "id": "ui-liveevents-vulture-token"
  },
  {
    "dlc_item": {
      "path": "/1636639820/uploads/ui-liveevents-vulture-tooltip.png",
      "version": "1636639820",
      "filesize": 46610,
      "base": "https://fallguys-assets.gamefuel.info/fallguys-uploads"
    },
    "id": "ui-liveevents-vulture-tooltip"
  },
  {
    "dlc_item": {
      "path": "/1645459368/uploads/ui-liveevents-weekofromance-bg.png",
      "version": "1645459368",
      "filesize": 196339,
      "base": "https://fallguys-assets.gamefuel.info/fallguys-uploads"
    },
    "id": "ui-liveevents-weekofromance-bg"
  },
  {
    "dlc_item": {
      "path": "/1643736950/uploads/ui-liveevents-weekofromance-costume.png",
      "version": "1643736950",
      "filesize": 481377,
      "base": "https://fallguys-assets.gamefuel.info/fallguys-uploads"
    },
    "id": "ui-liveevents-weekofromance-costume"
  },
  {
    "dlc_item": {
      "path": "/1641837062/uploads/ui-liveevents-weekofromance-token.png",
      "version": "1641837062",
      "filesize": 22049,
      "base": "https://fallguys-assets.gamefuel.info/fallguys-uploads"
    },
    "id": "ui-liveevents-weekofromance-token"
  },
  {
    "dlc_item": {
      "path": "/1641837078/uploads/ui-liveevents-weekofromance-tooltip.png",
      "version": "1641837078",
      "filesize": 34489,
      "base": "https://fallguys-assets.gamefuel.info/fallguys-uploads"
    },
    "id": "ui-liveevents-weekofromance-tooltip"
  },
  {
    "dlc_item": {
      "path": "/1632756490/uploads/ui-liveevents-wok1-bg.png",
      "version": "1632756490",
      "filesize": 300494,
      "base": "https://fallguys-assets.gamefuel.info/fallguys-uploads"
    },
    "id": "ui-liveevents-wok1-bg"
  },
  {
    "dlc_item": {
      "path": "/1632756653/uploads/ui-liveevents-wok1-costume.png",
      "version": "1632756653",
      "filesize": 282269,
      "base": "https://fallguys-assets.gamefuel.info/fallguys-uploads"
    },
    "id": "ui-liveevents-wok1-costume"
  },
  {
    "dlc_item": {
      "path": "/1633076492/uploads/ui-liveevents-wok1-tooltip.png",
      "version": "1633076492",
      "filesize": 56034,
      "base": "https://fallguys-assets.gamefuel.info/fallguys-uploads"
    },
    "id": "ui-liveevents-wok1-tooltip"
  },
  {
    "dlc_item": {
      "path": "/1632756515/uploads/ui-liveevents-wok2-bg.png",
      "version": "1632756515",
      "filesize": 393603,
      "base": "https://fallguys-assets.gamefuel.info/fallguys-uploads"
    },
    "id": "ui-liveevents-wok2-bg"
  },
  {
    "dlc_item": {
      "path": "/1632756665/uploads/ui-liveevents-wok2-costume.png",
      "version": "1632756665",
      "filesize": 564032,
      "base": "https://fallguys-assets.gamefuel.info/fallguys-uploads"
    },
    "id": "ui-liveevents-wok2-costume"
  },
  {
    "dlc_item": {
      "path": "/1633076508/uploads/ui-liveevents-wok2-tooltip.png",
      "version": "1633076508",
      "filesize": 54389,
      "base": "https://fallguys-assets.gamefuel.info/fallguys-uploads"
    },
    "id": "ui-liveevents-wok2-tooltip"
  },
  {
    "dlc_item": {
      "path": "/1632756548/uploads/ui-liveevents-wok3-bg.png",
      "version": "1632756548",
      "filesize": 416635,
      "base": "https://fallguys-assets.gamefuel.info/fallguys-uploads"
    },
    "id": "ui-liveevents-wok3-bg"
  },
  {
    "dlc_item": {
      "path": "/1632756678/uploads/ui-liveevents-wok3-costume.png",
      "version": "1632756678",
      "filesize": 391309,
      "base": "https://fallguys-assets.gamefuel.info/fallguys-uploads"
    },
    "id": "ui-liveevents-wok3-costume"
  },
  {
    "dlc_item": {
      "path": "/1633076520/uploads/ui-liveevents-wok3-tooltip.png",
      "version": "1633076520",
      "filesize": 56459,
      "base": "https://fallguys-assets.gamefuel.info/fallguys-uploads"
    },
    "id": "ui-liveevents-wok3-tooltip"
  },
  {
    "dlc_item": {
      "path": "/1632756561/uploads/ui-liveevents-wok4-bg.png",
      "version": "1632756561",
      "filesize": 342829,
      "base": "https://fallguys-assets.gamefuel.info/fallguys-uploads"
    },
    "id": "ui-liveevents-wok4-bg"
  },
  {
    "dlc_item": {
      "path": "/1632756688/uploads/ui-liveevents-wok4-costume.png",
      "version": "1632756688",
      "filesize": 825814,
      "base": "https://fallguys-assets.gamefuel.info/fallguys-uploads"
    },
    "id": "ui-liveevents-wok4-costume"
  },
  {
    "dlc_item": {
      "path": "/1633076530/uploads/ui-liveevents-wok4-tooltip.png",
      "version": "1633076530",
      "filesize": 55207,
      "base": "https://fallguys-assets.gamefuel.info/fallguys-uploads"
    },
    "id": "ui-liveevents-wok4-tooltip"
  },
  {
    "dlc_item": {
      "path": "/1632756576/uploads/ui-liveevents-wok5-bg.png",
      "version": "1632756576",
      "filesize": 264610,
      "base": "https://fallguys-assets.gamefuel.info/fallguys-uploads"
    },
    "id": "ui-liveevents-wok5-bg"
  },
  {
    "dlc_item": {
      "path": "/1632756702/uploads/ui-liveevents-wok5-costume.png",
      "version": "1632756702",
      "filesize": 1442721,
      "base": "https://fallguys-assets.gamefuel.info/fallguys-uploads"
    },
    "id": "ui-liveevents-wok5-costume"
  },
  {
    "dlc_item": {
      "path": "/1633076539/uploads/ui-liveevents-wok5-tooltip.png",
      "version": "1633076539",
      "filesize": 54959,
      "base": "https://fallguys-assets.gamefuel.info/fallguys-uploads"
    },
    "id": "ui-liveevents-wok5-tooltip"
  },
  {
    "dlc_item": {
      "path": "/1647968224/uploads/ui-newsfeed-le-stars-1.png",
      "version": "1647968224",
      "filesize": 188428,
      "base": "https://fallguys-assets.gamefuel.info/fallguys-uploads"
    },
    "id": "ui-newsfeed-le-stars-1"
  },
  {
    "dlc_item": {
      "path": "/1650385868/uploads/ui-newsfeed-le-stars-2.png",
      "version": "1650385868",
      "filesize": 175946,
      "base": "https://fallguys-assets.gamefuel.info/fallguys-uploads"
    },
    "id": "ui-newsfeed-le-stars-2"
  },
  {
    "dlc_item": {
      "path": "/1641400583/uploads/ui_liveevents_bg_invisibeans.png",
      "version": "1641400583",
      "filesize": 156259,
      "base": "https://fallguys-assets.gamefuel.info/fallguys-uploads"
    },
    "id": "ui_liveevents_bg_invisibeans"
  },
  {
    "dlc_item": {
      "path": "/1641400849/uploads/ui_liveevents_costume_astro.png",
      "version": "1641400849",
      "filesize": 588119,
      "base": "https://fallguys-assets.gamefuel.info/fallguys-uploads"
    },
    "id": "ui_liveevents_costume_astro"
  },
  {
    "dlc_item": {
      "path": "/1639087281/uploads/ui_liveevents_glizzy_background.png",
      "version": "1639087281",
      "filesize": 22840,
      "base": "https://fallguys-assets.gamefuel.info/fallguys-uploads"
    },
    "id": "ui_liveevents_glizzy_background"
  },
  {
    "dlc_item": {
      "path": "/1639087366/uploads/ui_liveevents_glizzy_promo.png",
      "version": "1639087366",
      "filesize": 810600,
      "base": "https://fallguys-assets.gamefuel.info/fallguys-uploads"
    },
    "id": "ui_liveevents_glizzy_promo"
  },
  {
    "dlc_item": {
      "path": "/1650379664/uploads/ui_liveevents_glizzy_promo_april_may.png",
      "version": "1650379664",
      "filesize": 551001,
      "base": "https://fallguys-assets.gamefuel.info/fallguys-uploads"
    },
    "id": "ui_liveevents_glizzy_promo_april_may"
  },
  {
    "dlc_item": {
      "path": "/1639087167/uploads/ui_liveevents_glizzy_s6_tooltip.png",
      "version": "1639087167",
      "filesize": 36948,
      "base": "https://fallguys-assets.gamefuel.info/fallguys-uploads"
    },
    "id": "ui_liveevents_glizzy_s6_tooltip"
  },
  {
    "dlc_item": {
      "path": "/1649675089/uploads/ui_liveevents_glizzy_s6_tooltip_april_may.png",
      "version": "1649675089",
      "filesize": 30424,
      "base": "https://fallguys-assets.gamefuel.info/fallguys-uploads"
    },
    "id": "ui_liveevents_glizzy_s6_tooltip_april_may"
  },
  {
    "dlc_item": {
      "path": "/1635861197/uploads/ui_liveevents_oriole_background.png",
      "version": "1635861197",
      "filesize": 197102,
      "base": "https://fallguys-assets.gamefuel.info/fallguys-uploads"
    },
    "id": "ui_liveevents_oriole_background"
  },
  {
    "dlc_item": {
      "path": "/1635179705/uploads/ui_liveevents_oriole_costume.png",
      "version": "1635179705",
      "filesize": 723992,
      "base": "https://fallguys-assets.gamefuel.info/fallguys-uploads"
    },
    "id": "ui_liveevents_oriole_costume"
  },
  {
    "dlc_item": {
      "path": "/1635179767/uploads/ui_liveevents_oriole_icon.png",
      "version": "1635179767",
      "filesize": 22433,
      "base": "https://fallguys-assets.gamefuel.info/fallguys-uploads"
    },
    "id": "ui_liveevents_oriole_icon"
  },
  {
    "dlc_item": {
      "path": "/1635179621/uploads/ui_liveevents_oriole_tooltip.png",
      "version": "1635179621",
      "filesize": 43459,
      "base": "https://fallguys-assets.gamefuel.info/fallguys-uploads"
    },
    "id": "ui_liveevents_oriole_tooltip"
  },
  {
    "dlc_item": {
      "path": "/1641400619/uploads/ui_liveevents_reward_sweet.png",
      "version": "1641400619",
      "filesize": 18107,
      "base": "https://fallguys-assets.gamefuel.info/fallguys-uploads"
    },
    "id": "ui_liveevents_reward_sweet"
  },
  {
    "dlc_item": {
      "path": "/1635180206/uploads/ui_liveevents_s5_endofseason_background.png",
      "version": "1635180206",
      "filesize": 161992,
      "base": "https://fallguys-assets.gamefuel.info/fallguys-uploads"
    },
    "id": "ui_liveevents_s5_endofseason_background"
  },
  {
    "dlc_item": {
      "path": "/1635180217/uploads/ui_liveevents_s5_endofseason_costume.png",
      "version": "1635180217",
      "filesize": 804658,
      "base": "https://fallguys-assets.gamefuel.info/fallguys-uploads"
    },
    "id": "ui_liveevents_s5_endofseason_costume"
  },
  {
    "dlc_item": {
      "path": "/1635672143/uploads/ui_liveevents_s5_endofseason_tooltip.png",
      "version": "1635672143",
      "filesize": 43432,
      "base": "https://fallguys-assets.gamefuel.info/fallguys-uploads"
    },
    "id": "ui_liveevents_s5_endofseason_tooltip"
  },
  {
    "dlc_item": {
      "path": "/1641400809/uploads/ui_liveevents_tooltip_invisibeans_astro.png",
      "version": "1641400809",
      "filesize": 42355,
      "base": "https://fallguys-assets.gamefuel.info/fallguys-uploads"
    },
    "id": "ui_liveevents_tooltip_invisibeans_astro"
  },
  {
    "dlc_item": {
      "path": "/1629904314/uploads/ui_newsfeed_amazon_april.png",
      "version": "1629904314",
      "filesize": 331816,
      "base": "https://fallguys-assets.gamefuel.info/fallguys-uploads"
    },
    "id": "ui_newsfeed_amazon_april"
  },
  {
    "dlc_item": {
      "path": "/1647260868/uploads/ui_newsfeed_amazon_april_s6.png",
      "version": "1647260868",
      "filesize": 316697,
      "base": "https://fallguys-assets.gamefuel.info/fallguys-uploads"
    },
    "id": "ui_newsfeed_amazon_april_s6"
  },
  {
    "dlc_item": {
      "path": "/1636636486/uploads/ui_newsfeed_amazon_december.png",
      "version": "1636636486",
      "filesize": 115236,
      "base": "https://fallguys-assets.gamefuel.info/fallguys-uploads"
    },
    "id": "ui_newsfeed_amazon_december"
  },
  {
    "dlc_item": {
      "path": "/1641482878/uploads/ui_newsfeed_amazon_february.png",
      "version": "1641482878",
      "filesize": 104932,
      "base": "https://fallguys-assets.gamefuel.info/fallguys-uploads"
    },
    "id": "ui_newsfeed_amazon_february"
  },
  {
    "dlc_item": {
      "path": "/1639048464/uploads/ui_newsfeed_amazon_january.png",
      "version": "1639048464",
      "filesize": 100216,
      "base": "https://fallguys-assets.gamefuel.info/fallguys-uploads"
    },
    "id": "ui_newsfeed_amazon_january"
  },
  {
    "dlc_item": {
      "path": "/1629928473/uploads/ui_newsfeed_amazon_july.png",
      "version": "1629928473",
      "filesize": 637505,
      "base": "https://fallguys-assets.gamefuel.info/fallguys-uploads"
    },
    "id": "ui_newsfeed_amazon_july"
  },
  {
    "dlc_item": {
      "path": "/1629904362/uploads/ui_newsfeed_amazon_june.png",
      "version": "1629904362",
      "filesize": 752139,
      "base": "https://fallguys-assets.gamefuel.info/fallguys-uploads"
    },
    "id": "ui_newsfeed_amazon_june"
  },
  {
    "dlc_item": {
      "path": "/1644570605/uploads/ui_newsfeed_amazon_march_s6.png",
      "version": "1644570605",
      "filesize": 916191,
      "base": "https://fallguys-assets.gamefuel.info/fallguys-uploads"
    },
    "id": "ui_newsfeed_amazon_march_s6"
  },
  {
    "dlc_item": {
      "path": "/1650039836/uploads/ui_newsfeed_amazon_may_s6.png",
      "version": "1650039836",
      "filesize": 328714,
      "base": "https://fallguys-assets.gamefuel.info/fallguys-uploads"
    },
    "id": "ui_newsfeed_amazon_may_s6"
  },
  {
    "dlc_item": {
      "path": "/1634661541/uploads/ui_newsfeed_amazon_november.png",
      "version": "1634661541",
      "filesize": 847701,
      "base": "https://fallguys-assets.gamefuel.info/fallguys-uploads"
    },
    "id": "ui_newsfeed_amazon_november"
  },
  {
    "dlc_item": {
      "path": "/1631101908/uploads/ui_newsfeed_amazon_october.png",
      "version": "1631101908",
      "filesize": 428096,
      "base": "https://fallguys-assets.gamefuel.info/fallguys-uploads"
    },
    "id": "ui_newsfeed_amazon_october"
  },
  {
    "dlc_item": {
      "path": "/1631098628/uploads/ui_newsfeed_amazon_september.png",
      "version": "1631098628",
      "filesize": 433879,
      "base": "https://fallguys-assets.gamefuel.info/fallguys-uploads"
    },
    "id": "ui_newsfeed_amazon_september"
  },
  {
    "dlc_item": {
      "path": "/1635352899/uploads/ui_newsfeed_bluejay_05.png",
      "version": "1635352899",
      "filesize": 116284,
      "base": "https://fallguys-assets.gamefuel.info/fallguys-uploads"
    },
    "id": "ui_newsfeed_bluejay_05"
  },
  {
    "dlc_item": {
      "path": "/1650385889/uploads/ui_newsfeed_bonus_fame.png",
      "version": "1650385889",
      "filesize": 196033,
      "base": "https://fallguys-assets.gamefuel.info/fallguys-uploads"
    },
    "id": "ui_newsfeed_bonus_fame"
  },
  {
    "dlc_item": {
      "path": "/1629928218/uploads/ui_newsfeed_budgie_event.png",
      "version": "1629928218",
      "filesize": 721817,
      "base": "https://fallguys-assets.gamefuel.info/fallguys-uploads"
    },
    "id": "ui_newsfeed_budgie_event"
  },
  {
    "dlc_item": {
      "path": "/1633973767/uploads/ui_newsfeed_budgie_s5.png",
      "version": "1633973767",
      "filesize": 139346,
      "base": "https://fallguys-assets.gamefuel.info/fallguys-uploads"
    },
    "id": "ui_newsfeed_budgie_s5"
  },
  {
    "dlc_item": {
      "path": "/1638985732/uploads/ui_newsfeed_chouch_01.png",
      "version": "1638985732",
      "filesize": 115009,
      "base": "https://fallguys-assets.gamefuel.info/fallguys-uploads"
    },
    "id": "ui_newsfeed_chouch_01"
  },
  {
    "dlc_item": {
      "path": "/1638985742/uploads/ui_newsfeed_chouch_02.png",
      "version": "1638985742",
      "filesize": 113536,
      "base": "https://fallguys-assets.gamefuel.info/fallguys-uploads"
    },
    "id": "ui_newsfeed_chouch_02"
  },
  {
    "dlc_item": {
      "path": "/1638985748/uploads/ui_newsfeed_chouch_03.png",
      "version": "1638985748",
      "filesize": 108867,
      "base": "https://fallguys-assets.gamefuel.info/fallguys-uploads"
    },
    "id": "ui_newsfeed_chouch_03"
  },
  {
    "dlc_item": {
      "path": "/1629217835/uploads/ui_newsfeed_crownladder_le.png",
      "version": "1629217835",
      "filesize": 611307,
      "base": "https://fallguys-assets.gamefuel.info/fallguys-uploads"
    },
    "id": "ui_newsfeed_crownladder_le"
  },
  {
    "dlc_item": {
      "path": "/1641570639/uploads/ui_newsfeed_dove_3_bot.png",
      "version": "1641570639",
      "filesize": 63022,
      "base": "https://fallguys-assets.gamefuel.info/fallguys-uploads"
    },
    "id": "ui_newsfeed_dove_3_bot"
  },
  {
    "dlc_item": {
      "path": "/1641570629/uploads/ui_newsfeed_dove_3_bot_and_dino.png",
      "version": "1641570629",
      "filesize": 104058,
      "base": "https://fallguys-assets.gamefuel.info/fallguys-uploads"
    },
    "id": "ui_newsfeed_dove_3_bot_and_dino"
  },
  {
    "dlc_item": {
      "path": "/1641570658/uploads/ui_newsfeed_dove_3_dino.png",
      "version": "1641570658",
      "filesize": 76330,
      "base": "https://fallguys-assets.gamefuel.info/fallguys-uploads"
    },
    "id": "ui_newsfeed_dove_3_dino"
  },
  {
    "dlc_item": {
      "path": "/1629903661/uploads/ui_newsfeed_dove_le_01.png",
      "version": "1629903661",
      "filesize": 1041602,
      "base": "https://fallguys-assets.gamefuel.info/fallguys-uploads"
    },
    "id": "ui_newsfeed_dove_le_01"
  },
  {
    "dlc_item": {
      "path": "/1629903771/uploads/ui_newsfeed_dove_le_02.png",
      "version": "1629903771",
      "filesize": 675812,
      "base": "https://fallguys-assets.gamefuel.info/fallguys-uploads"
    },
    "id": "ui_newsfeed_dove_le_02"
  },
  {
    "dlc_item": {
      "path": "/1628246074/uploads/ui_newsfeed_dove_reward.png",
      "version": "1628246074",
      "filesize": 418306,
      "base": "https://fallguys-assets.gamefuel.info/fallguys-uploads"
    },
    "id": "ui_newsfeed_dove_reward"
  },
  {
    "dlc_item": {
      "path": "/1629905129/uploads/ui_newsfeed_easter_event.png",
      "version": "1629905129",
      "filesize": 454602,
      "base": "https://fallguys-assets.gamefuel.info/fallguys-uploads"
    },
    "id": "ui_newsfeed_easter_event"
  },
  {
    "dlc_item": {
      "path": "/1629904441/uploads/ui_newsfeed_event_crow.png",
      "version": "1629904441",
      "filesize": 510136,
      "base": "https://fallguys-assets.gamefuel.info/fallguys-uploads"
    },
    "id": "ui_newsfeed_event_crow"
  },
  {
    "dlc_item": {
      "path": "/1645198013/uploads/ui_newsfeed_fan_favourites_survey_qr.png",
      "version": "1645198013",
      "filesize": 126406,
      "base": "https://fallguys-assets.gamefuel.info/fallguys-uploads"
    },
    "id": "ui_newsfeed_fan_favourites_survey_qr"
  },
  {
    "dlc_item": {
      "path": "/1629278538/uploads/ui_newsfeed_gamescom.png",
      "version": "1629278538",
      "filesize": 2486238,
      "base": "https://fallguys-assets.gamefuel.info/fallguys-uploads"
    },
    "id": "ui_newsfeed_gamescom"
  },
  {
    "dlc_item": {
      "path": "/1639088897/uploads/ui_newsfeed_glizzy_s6.png",
      "version": "1639088897",
      "filesize": 78998,
      "base": "https://fallguys-assets.gamefuel.info/fallguys-uploads"
    },
    "id": "ui_newsfeed_glizzy_s6"
  },
  {
    "dlc_item": {
      "path": "/1650366832/uploads/ui_newsfeed_glizzy_s6_april_may.png",
      "version": "1650366832",
      "filesize": 338642,
      "base": "https://fallguys-assets.gamefuel.info/fallguys-uploads"
    },
    "id": "ui_newsfeed_glizzy_s6_april_may"
  },
  {
    "dlc_item": {
      "path": "/1630516598/uploads/ui_newsfeed_goldfinch_1.png",
      "version": "1630516598",
      "filesize": 1148145,
      "base": "https://fallguys-assets.gamefuel.info/fallguys-uploads"
    },
    "id": "ui_newsfeed_goldfinch_1"
  },
  {
    "dlc_item": {
      "path": "/1639394411/uploads/ui_newsfeed_guestravaganza_01.png",
      "version": "1639394411",
      "filesize": 1650560,
      "base": "https://fallguys-assets.gamefuel.info/fallguys-uploads"
    },
    "id": "ui_newsfeed_guestravaganza_01"
  },
  {
    "dlc_item": {
      "path": "/1639084153/uploads/ui_newsfeed_guestravaganza_02.png",
      "version": "1639084153",
      "filesize": 963200,
      "base": "https://fallguys-assets.gamefuel.info/fallguys-uploads"
    },
    "id": "ui_newsfeed_guestravaganza_02"
  },
  {
    "dlc_item": {
      "path": "/1639084168/uploads/ui_newsfeed_guestravaganza_03.png",
      "version": "1639084168",
      "filesize": 939603,
      "base": "https://fallguys-assets.gamefuel.info/fallguys-uploads"
    },
    "id": "ui_newsfeed_guestravaganza_03"
  },
  {
    "dlc_item": {
      "path": "/1630516907/uploads/ui_newsfeed_kakapo_1.png",
      "version": "1630516907",
      "filesize": 933468,
      "base": "https://fallguys-assets.gamefuel.info/fallguys-uploads"
    },
    "id": "ui_newsfeed_kakapo_1"
  },
  {
    "dlc_item": {
      "path": "/1630516917/uploads/ui_newsfeed_kakapo_2.png",
      "version": "1630516917",
      "filesize": 692378,
      "base": "https://fallguys-assets.gamefuel.info/fallguys-uploads"
    },
    "id": "ui_newsfeed_kakapo_2"
  },
  {
    "dlc_item": {
      "path": "/1630516926/uploads/ui_newsfeed_kakapo_3.png",
      "version": "1630516926",
      "filesize": 811674,
      "base": "https://fallguys-assets.gamefuel.info/fallguys-uploads"
    },
    "id": "ui_newsfeed_kakapo_3"
  },
  {
    "dlc_item": {
      "path": "/1632735041/uploads/ui_newsfeed_kestral.png",
      "version": "1632735041",
      "filesize": 78303,
      "base": "https://fallguys-assets.gamefuel.info/fallguys-uploads"
    },
    "id": "ui_newsfeed_kestral"
  },
  {
    "dlc_item": {
      "path": "/1633967948/uploads/ui_newsfeed_le_halloween.png",
      "version": "1633967948",
      "filesize": 691681,
      "base": "https://fallguys-assets.gamefuel.info/fallguys-uploads"
    },
    "id": "ui_newsfeed_le_halloween"
  },
  {
    "dlc_item": {
      "path": "/1633595170/uploads/ui_newsfeed_le_halloween_costume.png",
      "version": "1633595170",
      "filesize": 1715922,
      "base": "https://fallguys-assets.gamefuel.info/fallguys-uploads"
    },
    "id": "ui_newsfeed_le_halloween_costume"
  },
  {
    "dlc_item": {
      "path": "/1633594079/uploads/ui_newsfeed_le_halloween_soon.png",
      "version": "1633594079",
      "filesize": 1445237,
      "base": "https://fallguys-assets.gamefuel.info/fallguys-uploads"
    },
    "id": "ui_newsfeed_le_halloween_soon"
  },
  {
    "dlc_item": {
      "path": "/1641570330/uploads/ui_newsfeed_le_invisibeans.png",
      "version": "1641570330",
      "filesize": 917703,
      "base": "https://fallguys-assets.gamefuel.info/fallguys-uploads"
    },
    "id": "ui_newsfeed_le_invisibeans"
  },
  {
    "dlc_item": {
      "path": "/1633430427/uploads/ui_newsfeed_le_wok_01.png",
      "version": "1633430427",
      "filesize": 175580,
      "base": "https://fallguys-assets.gamefuel.info/fallguys-uploads"
    },
    "id": "ui_newsfeed_le_wok_01"
  },
  {
    "dlc_item": {
      "path": "/1632820397/uploads/ui_newsfeed_le_wok_02.png",
      "version": "1632820397",
      "filesize": 181927,
      "base": "https://fallguys-assets.gamefuel.info/fallguys-uploads"
    },
    "id": "ui_newsfeed_le_wok_02"
  },
  {
    "dlc_item": {
      "path": "/1632820409/uploads/ui_newsfeed_le_wok_03.png",
      "version": "1632820409",
      "filesize": 186716,
      "base": "https://fallguys-assets.gamefuel.info/fallguys-uploads"
    },
    "id": "ui_newsfeed_le_wok_03"
  },
  {
    "dlc_item": {
      "path": "/1632820416/uploads/ui_newsfeed_le_wok_04.png",
      "version": "1632820416",
      "filesize": 187567,
      "base": "https://fallguys-assets.gamefuel.info/fallguys-uploads"
    },
    "id": "ui_newsfeed_le_wok_04"
  },
  {
    "dlc_item": {
      "path": "/1632820423/uploads/ui_newsfeed_le_wok_05.png",
      "version": "1632820423",
      "filesize": 187116,
      "base": "https://fallguys-assets.gamefuel.info/fallguys-uploads"
    },
    "id": "ui_newsfeed_le_wok_05"
  },
  {
    "dlc_item": {
      "path": "/1633447369/uploads/ui_newsfeed_le_wok_soon.png",
      "version": "1633447369",
      "filesize": 1954405,
      "base": "https://fallguys-assets.gamefuel.info/fallguys-uploads"
    },
    "id": "ui_newsfeed_le_wok_soon"
  },
  {
    "dlc_item": {
      "path": "/1641480231/uploads/ui_newsfeed_longguy.png",
      "version": "1641480231",
      "filesize": 94746,
      "base": "https://fallguys-assets.gamefuel.info/fallguys-uploads"
    },
    "id": "ui_newsfeed_longguy"
  },
  {
    "dlc_item": {
      "path": "/1629904164/uploads/ui_newsfeed_magpie_event.png",
      "version": "1629904164",
      "filesize": 897356,
      "base": "https://fallguys-assets.gamefuel.info/fallguys-uploads"
    },
    "id": "ui_newsfeed_magpie_event"
  },
  {
    "dlc_item": {
      "path": "/1638442417/uploads/ui_newsfeed_newyears6_event.png",
      "version": "1638442417",
      "filesize": 1914994,
      "base": "https://fallguys-assets.gamefuel.info/fallguys-uploads"
    },
    "id": "ui_newsfeed_newyears6_event"
  },
  {
    "dlc_item": {
      "path": "/1635180774/uploads/ui_newsfeed_oriole.png",
      "version": "1635180774",
      "filesize": 1025309,
      "base": "https://fallguys-assets.gamefuel.info/fallguys-uploads"
    },
    "id": "ui_newsfeed_oriole"
  },
  {
    "dlc_item": {
      "path": "/1629279296/uploads/ui_newsfeed_ostrich_fame.png",
      "version": "1629279296",
      "filesize": 122074,
      "base": "https://fallguys-assets.gamefuel.info/fallguys-uploads"
    },
    "id": "ui_newsfeed_ostrich_fame"
  },
  {
    "dlc_item": {
      "path": "/1629904273/uploads/ui_newsfeed_peacock_event.png",
      "version": "1629904273",
      "filesize": 684474,
      "base": "https://fallguys-assets.gamefuel.info/fallguys-uploads"
    },
    "id": "ui_newsfeed_peacock_event"
  },
  {
    "dlc_item": {
      "path": "/1630948647/uploads/ui_newsfeed_phoenix.png",
      "version": "1630948647",
      "filesize": 113487,
      "base": "https://fallguys-assets.gamefuel.info/fallguys-uploads"
    },
    "id": "ui_newsfeed_phoenix"
  },
  {
    "dlc_item": {
      "path": "/1650385912/uploads/ui_newsfeed_ps4_app_migration.png",
      "version": "1650385912",
      "filesize": 164784,
      "base": "https://fallguys-assets.gamefuel.info/fallguys-uploads"
    },
    "id": "ui_newsfeed_ps4_app_migration"
  },
  {
    "dlc_item": {
      "path": "/1635351413/uploads/ui_newsfeed_pigeon_01.png",
      "version": "1635351413",
      "filesize": 250499,
      "base": "https://fallguys-assets.gamefuel.info/fallguys-uploads"
    },
    "id": "ui_newsfeed_racepigeon_01"
  },
  {
    "dlc_item": {
      "path": "/1629903589/uploads/ui_newsfeed_robin_event.png",
      "version": "1629903589",
      "filesize": 729833,
      "base": "https://fallguys-assets.gamefuel.info/fallguys-uploads"
    },
    "id": "ui_newsfeed_robin_event"
  },
  {
    "dlc_item": {
      "path": "/1629928889/uploads/ui_newsfeed_s3_aimlab.png",
      "version": "1629928889",
      "filesize": 434587,
      "base": "https://fallguys-assets.gamefuel.info/fallguys-uploads"
    },
    "id": "ui_newsfeed_s3_aimlab"
  },
  {
    "dlc_item": {
      "path": "/1629928713/uploads/ui_newsfeed_s3_amazon_feb.png",
      "version": "1629928713",
      "filesize": 500955,
      "base": "https://fallguys-assets.gamefuel.info/fallguys-uploads"
    },
    "id": "ui_newsfeed_s3_amazon_feb"
  },
  {
    "dlc_item": {
      "path": "/1629912575/uploads/ui_newsfeed_s3_amazon_prime_v1.png",
      "version": "1629912575",
      "filesize": 591019,
      "base": "https://fallguys-assets.gamefuel.info/fallguys-uploads"
    },
    "id": "ui_newsfeed_s3_amazon_prime_v1"
  },
  {
    "dlc_item": {
      "path": "/1629928798/uploads/ui_newsfeed_s3_amazon_prime_v2.png",
      "version": "1629928798",
      "filesize": 462866,
      "base": "https://fallguys-assets.gamefuel.info/fallguys-uploads"
    },
    "id": "ui_newsfeed_s3_amazon_prime_v2"
  },
  {
    "dlc_item": {
      "path": "/1629904390/uploads/ui_newsfeed_s3_cuphead.png",
      "version": "1629904390",
      "filesize": 597192,
      "base": "https://fallguys-assets.gamefuel.info/fallguys-uploads"
    },
    "id": "ui_newsfeed_s3_cuphead"
  },
  {
    "dlc_item": {
      "path": "/1629928779/uploads/ui_newsfeed_s3_dlc_icy_adventure.png",
      "version": "1629928779",
      "filesize": 587828,
      "base": "https://fallguys-assets.gamefuel.info/fallguys-uploads"
    },
    "id": "ui_newsfeed_s3_dlc_icy_adventure"
  },
  {
    "dlc_item": {
      "path": "/1629928556/uploads/ui_newsfeed_s3_doom.png",
      "version": "1629928556",
      "filesize": 638045,
      "base": "https://fallguys-assets.gamefuel.info/fallguys-uploads"
    },
    "id": "ui_newsfeed_s3_doom"
  },
  {
    "dlc_item": {
      "path": "/1629912502/uploads/ui_newsfeed_s3_double_kudos.png",
      "version": "1629912502",
      "filesize": 926670,
      "base": "https://fallguys-assets.gamefuel.info/fallguys-uploads"
    },
    "id": "ui_newsfeed_s3_double_kudos"
  },
  {
    "dlc_item": {
      "path": "/1629912590/uploads/ui_newsfeed_s3_fan_favourites.png",
      "version": "1629912590",
      "filesize": 612974,
      "base": "https://fallguys-assets.gamefuel.info/fallguys-uploads"
    },
    "id": "ui_newsfeed_s3_fan_favourites"
  },
  {
    "dlc_item": {
      "path": "/1629928883/uploads/ui_newsfeed_s3_g2.png",
      "version": "1629928883",
      "filesize": 438441,
      "base": "https://fallguys-assets.gamefuel.info/fallguys-uploads"
    },
    "id": "ui_newsfeed_s3_g2"
  },
  {
    "dlc_item": {
      "path": "/1629928307/uploads/ui_newsfeed_s3_gauntlet_showdown.png",
      "version": "1629928307",
      "filesize": 584223,
      "base": "https://fallguys-assets.gamefuel.info/fallguys-uploads"
    },
    "id": "ui_newsfeed_s3_gauntlet_showdown"
  },
  {
    "dlc_item": {
      "path": "/1629928773/uploads/ui_newsfeed_s3_happy_new_year.png",
      "version": "1629928773",
      "filesize": 414068,
      "base": "https://fallguys-assets.gamefuel.info/fallguys-uploads"
    },
    "id": "ui_newsfeed_s3_happy_new_year"
  },
  {
    "dlc_item": {
      "path": "/1629928740/uploads/ui_newsfeed_s3_is_here.png",
      "version": "1629928740",
      "filesize": 566012,
      "base": "https://fallguys-assets.gamefuel.info/fallguys-uploads"
    },
    "id": "ui_newsfeed_s3_is_here"
  },
  {
    "dlc_item": {
      "path": "/1629928546/uploads/ui_newsfeed_s3_jump_around.png",
      "version": "1629928546",
      "filesize": 555249,
      "base": "https://fallguys-assets.gamefuel.info/fallguys-uploads"
    },
    "id": "ui_newsfeed_s3_jump_around"
  },
  {
    "dlc_item": {
      "path": "/1629912522/uploads/ui_newsfeed_s3_mid_season_update.png",
      "version": "1629912522",
      "filesize": 404396,
      "base": "https://fallguys-assets.gamefuel.info/fallguys-uploads"
    },
    "id": "ui_newsfeed_s3_mid_season_update"
  },
  {
    "dlc_item": {
      "path": "/1629928424/uploads/ui_newsfeed_s3_mix_it_up.png",
      "version": "1629928424",
      "filesize": 589783,
      "base": "https://fallguys-assets.gamefuel.info/fallguys-uploads"
    },
    "id": "ui_newsfeed_s3_mix_it_up"
  },
  {
    "dlc_item": {
      "path": "/1629928878/uploads/ui_newsfeed_s3_monkey_king.png",
      "version": "1629928878",
      "filesize": 1162737,
      "base": "https://fallguys-assets.gamefuel.info/fallguys-uploads"
    },
    "id": "ui_newsfeed_s3_monkey_king"
  },
  {
    "dlc_item": {
      "path": "/1629928850/uploads/ui_newsfeed_s3_mrbeast.png",
      "version": "1629928850",
      "filesize": 409820,
      "base": "https://fallguys-assets.gamefuel.info/fallguys-uploads"
    },
    "id": "ui_newsfeed_s3_mrbeast"
  },
  {
    "dlc_item": {
      "path": "/1629928232/uploads/ui_newsfeed_s3_roll_call.png",
      "version": "1629928232",
      "filesize": 602048,
      "base": "https://fallguys-assets.gamefuel.info/fallguys-uploads"
    },
    "id": "ui_newsfeed_s3_roll_call"
  },
  {
    "dlc_item": {
      "path": "/1629928685/uploads/ui_newsfeed_s3_santa.png",
      "version": "1629928685",
      "filesize": 484916,
      "base": "https://fallguys-assets.gamefuel.info/fallguys-uploads"
    },
    "id": "ui_newsfeed_s3_santa"
  },
  {
    "dlc_item": {
      "path": "/1629928786/uploads/ui_newsfeed_s3_show_fall_ball_cup.png",
      "version": "1629928786",
      "filesize": 528773,
      "base": "https://fallguys-assets.gamefuel.info/fallguys-uploads"
    },
    "id": "ui_newsfeed_s3_show_fall_ball_cup"
  },
  {
    "dlc_item": {
      "path": "/1629928518/uploads/ui_newsfeed_s3_show_fruit_basket.png",
      "version": "1629928518",
      "filesize": 646073,
      "base": "https://fallguys-assets.gamefuel.info/fallguys-uploads"
    },
    "id": "ui_newsfeed_s3_show_fruit_basket"
  },
  {
    "dlc_item": {
      "path": "/1629928708/uploads/ui_newsfeed_s3_show_hard_mode.png",
      "version": "1629928708",
      "filesize": 609151,
      "base": "https://fallguys-assets.gamefuel.info/fallguys-uploads"
    },
    "id": "ui_newsfeed_s3_show_hard_mode"
  },
  {
    "dlc_item": {
      "path": "/1629928753/uploads/ui_newsfeed_s3_show_hex_a_gone.png",
      "version": "1629928753",
      "filesize": 530428,
      "base": "https://fallguys-assets.gamefuel.info/fallguys-uploads"
    },
    "id": "ui_newsfeed_s3_show_hex_a_gone"
  },
  {
    "dlc_item": {
      "path": "/1629928720/uploads/ui_newsfeed_s3_show_ninja.png",
      "version": "1629928720",
      "filesize": 560545,
      "base": "https://fallguys-assets.gamefuel.info/fallguys-uploads"
    },
    "id": "ui_newsfeed_s3_show_ninja"
  },
  {
    "dlc_item": {
      "path": "/1629928698/uploads/ui_newsfeed_s3_show_winter_knockout.png",
      "version": "1629928698",
      "filesize": 594154,
      "base": "https://fallguys-assets.gamefuel.info/fallguys-uploads"
    },
    "id": "ui_newsfeed_s3_show_winter_knockout"
  },
  {
    "dlc_item": {
      "path": "/1629928692/uploads/ui_newsfeed_s3_sugar_plum_dlc.png",
      "version": "1629928692",
      "filesize": 728370,
      "base": "https://fallguys-assets.gamefuel.info/fallguys-uploads"
    },
    "id": "ui_newsfeed_s3_sugar_plum_dlc"
  },
  {
    "dlc_item": {
      "path": "/1629928300/uploads/ui_newsfeed_s3_thin_ice.png",
      "version": "1629928300",
      "filesize": 583733,
      "base": "https://fallguys-assets.gamefuel.info/fallguys-uploads"
    },
    "id": "ui_newsfeed_s3_thin_ice"
  },
  {
    "dlc_item": {
      "path": "/1629928726/uploads/ui_newsfeed_s3_valentines.png",
      "version": "1629928726",
      "filesize": 632366,
      "base": "https://fallguys-assets.gamefuel.info/fallguys-uploads"
    },
    "id": "ui_newsfeed_s3_valentines"
  },
  {
    "dlc_item": {
      "path": "/1629912543/uploads/ui_newsfeed_s4_4041.png",
      "version": "1629912543",
      "filesize": 654768,
      "base": "https://fallguys-assets.gamefuel.info/fallguys-uploads"
    },
    "id": "ui_newsfeed_s4_4041"
  },
  {
    "dlc_item": {
      "path": "/1629904291/uploads/ui_newsfeed_s4_amazon_march.png",
      "version": "1629904291",
      "filesize": 450822,
      "base": "https://fallguys-assets.gamefuel.info/fallguys-uploads"
    },
    "id": "ui_newsfeed_s4_amazon_march"
  },
  {
    "dlc_item": {
      "path": "/1629904222/uploads/ui_newsfeed_s4_cardinal.png",
      "version": "1629904222",
      "filesize": 817000,
      "base": "https://fallguys-assets.gamefuel.info/fallguys-uploads"
    },
    "id": "ui_newsfeed_s4_cardinal"
  },
  {
    "dlc_item": {
      "path": "/1629904419/uploads/ui_newsfeed_s4_devolver.png",
      "version": "1629904419",
      "filesize": 915511,
      "base": "https://fallguys-assets.gamefuel.info/fallguys-uploads"
    },
    "id": "ui_newsfeed_s4_devolver"
  },
  {
    "dlc_item": {
      "path": "/1629928529/uploads/ui_newsfeed_s4_future_fashion.png",
      "version": "1629928529",
      "filesize": 748310,
      "base": "https://fallguys-assets.gamefuel.info/fallguys-uploads"
    },
    "id": "ui_newsfeed_s4_future_fashion"
  },
  {
    "dlc_item": {
      "path": "/1629904374/uploads/ui_newsfeed_s4_key.png",
      "version": "1629904374",
      "filesize": 827898,
      "base": "https://fallguys-assets.gamefuel.info/fallguys-uploads"
    },
    "id": "ui_newsfeed_s4_key"
  },
  {
    "dlc_item": {
      "path": "/1629904144/uploads/ui_newsfeed_s4_kingfisher_quad.png",
      "version": "1629904144",
      "filesize": 740089,
      "base": "https://fallguys-assets.gamefuel.info/fallguys-uploads"
    },
    "id": "ui_newsfeed_s4_kingfisher_quad"
  },
  {
    "dlc_item": {
      "path": "/1629903793/uploads/ui_newsfeed_s4_kingfisher_trio.png",
      "version": "1629903793",
      "filesize": 681999,
      "base": "https://fallguys-assets.gamefuel.info/fallguys-uploads"
    },
    "id": "ui_newsfeed_s4_kingfisher_trio"
  },
  {
    "dlc_item": {
      "path": "/1629928805/uploads/ui_newsfeed_s4_pop_star.png",
      "version": "1629928805",
      "filesize": 684797,
      "base": "https://fallguys-assets.gamefuel.info/fallguys-uploads"
    },
    "id": "ui_newsfeed_s4_pop_star"
  },
  {
    "dlc_item": {
      "path": "/1629928486/uploads/ui_newsfeed_s4_slam_dunk.png",
      "version": "1629928486",
      "filesize": 605071,
      "base": "https://fallguys-assets.gamefuel.info/fallguys-uploads"
    },
    "id": "ui_newsfeed_s4_slam_dunk"
  },
  {
    "dlc_item": {
      "path": "/1629928567/uploads/ui_newsfeed_s4_slime_trials.png",
      "version": "1629928567",
      "filesize": 534994,
      "base": "https://fallguys-assets.gamefuel.info/fallguys-uploads"
    },
    "id": "ui_newsfeed_s4_slime_trials"
  },
  {
    "dlc_item": {
      "path": "/1629904300/uploads/ui_newsfeed_s4_space_traveller.png",
      "version": "1629904300",
      "filesize": 405351,
      "base": "https://fallguys-assets.gamefuel.info/fallguys-uploads"
    },
    "id": "ui_newsfeed_s4_space_traveller"
  },
  {
    "dlc_item": {
      "path": "/1629903905/uploads/ui_newsfeed_s4_squads.png",
      "version": "1629903905",
      "filesize": 740089,
      "base": "https://fallguys-assets.gamefuel.info/fallguys-uploads"
    },
    "id": "ui_newsfeed_s4_squads"
  },
  {
    "dlc_item": {
      "path": "/1629928278/uploads/ui_newsfeed_s4_tail_tag.png",
      "version": "1629928278",
      "filesize": 578913,
      "base": "https://fallguys-assets.gamefuel.info/fallguys-uploads"
    },
    "id": "ui_newsfeed_s4_tail_tag"
  },
  {
    "dlc_item": {
      "path": "/1629928792/uploads/ui_newsfeed_s4_twitch.png",
      "version": "1629928792",
      "filesize": 473339,
      "base": "https://fallguys-assets.gamefuel.info/fallguys-uploads"
    },
    "id": "ui_newsfeed_s4_twitch"
  },
  {
    "dlc_item": {
      "path": "/1629928593/uploads/ui_newsfeed_s5_dlc_capers.png",
      "version": "1629928593",
      "filesize": 741029,
      "base": "https://fallguys-assets.gamefuel.info/fallguys-uploads"
    },
    "id": "ui_newsfeed_s5_dlc_capers"
  },
  {
    "dlc_item": {
      "path": "/1629928599/uploads/ui_newsfeed_s5_dlc_pirates.png",
      "version": "1629928599",
      "filesize": 692375,
      "base": "https://fallguys-assets.gamefuel.info/fallguys-uploads"
    },
    "id": "ui_newsfeed_s5_dlc_pirates"
  },
  {
    "dlc_item": {
      "path": "/1635671882/uploads/ui_newsfeed_s5_end_of_season_01.png",
      "version": "1635671882",
      "filesize": 525790,
      "base": "https://fallguys-assets.gamefuel.info/fallguys-uploads"
    },
    "id": "ui_newsfeed_s5_end_of_season_01"
  },
  {
    "dlc_item": {
      "path": "/1635671891/uploads/ui_newsfeed_s5_end_of_season_02.png",
      "version": "1635671891",
      "filesize": 246565,
      "base": "https://fallguys-assets.gamefuel.info/fallguys-uploads"
    },
    "id": "ui_newsfeed_s5_end_of_season_02"
  },
  {
    "dlc_item": {
      "path": "/1635671903/uploads/ui_newsfeed_s5_end_of_season_03.png",
      "version": "1635671903",
      "filesize": 260603,
      "base": "https://fallguys-assets.gamefuel.info/fallguys-uploads"
    },
    "id": "ui_newsfeed_s5_end_of_season_03"
  },
  {
    "dlc_item": {
      "path": "/1635671909/uploads/ui_newsfeed_s5_end_of_season_04.png",
      "version": "1635671909",
      "filesize": 272770,
      "base": "https://fallguys-assets.gamefuel.info/fallguys-uploads"
    },
    "id": "ui_newsfeed_s5_end_of_season_04"
  },
  {
    "dlc_item": {
      "path": "/1635671916/uploads/ui_newsfeed_s5_end_of_season_05.png",
      "version": "1635671916",
      "filesize": 324735,
      "base": "https://fallguys-assets.gamefuel.info/fallguys-uploads"
    },
    "id": "ui_newsfeed_s5_end_of_season_05"
  },
  {
    "dlc_item": {
      "path": "/1635671925/uploads/ui_newsfeed_s5_end_of_season_06.png",
      "version": "1635671925",
      "filesize": 349596,
      "base": "https://fallguys-assets.gamefuel.info/fallguys-uploads"
    },
    "id": "ui_newsfeed_s5_end_of_season_06"
  },
  {
    "dlc_item": {
      "path": "/1629928244/uploads/ui_newsfeed_s5_fame_path.png",
      "version": "1629928244",
      "filesize": 845822,
      "base": "https://fallguys-assets.gamefuel.info/fallguys-uploads"
    },
    "id": "ui_newsfeed_s5_fame_path"
  },
  {
    "dlc_item": {
      "path": "/1629904336/uploads/ui_newsfeed_s5_is_here.png",
      "version": "1629904336",
      "filesize": 989935,
      "base": "https://fallguys-assets.gamefuel.info/fallguys-uploads"
    },
    "id": "ui_newsfeed_s5_is_here"
  },
  {
    "dlc_item": {
      "path": "/1632836819/uploads/ui_newsfeed_s5_ostrich_2.png",
      "version": "1632836819",
      "filesize": 98673,
      "base": "https://fallguys-assets.gamefuel.info/fallguys-uploads"
    },
    "id": "ui_newsfeed_s5_ostrich_2"
  },
  {
    "dlc_item": {
      "path": "/1629928453/uploads/ui_newsfeed_s5_show_anniversary.png",
      "version": "1629928453",
      "filesize": 588573,
      "base": "https://fallguys-assets.gamefuel.info/fallguys-uploads"
    },
    "id": "ui_newsfeed_s5_show_anniversary"
  },
  {
    "dlc_item": {
      "path": "/1629928573/uploads/ui_newsfeed_s5_show_beasty.png",
      "version": "1629928573",
      "filesize": 577352,
      "base": "https://fallguys-assets.gamefuel.info/fallguys-uploads"
    },
    "id": "ui_newsfeed_s5_show_beasty"
  },
  {
    "dlc_item": {
      "path": "/1629912532/uploads/ui_newsfeed_s5_show_bubble_trouble.png",
      "version": "1629912532",
      "filesize": 746378,
      "base": "https://fallguys-assets.gamefuel.info/fallguys-uploads"
    },
    "id": "ui_newsfeed_s5_show_bubble_trouble"
  },
  {
    "dlc_item": {
      "path": "/1629928444/uploads/ui_newsfeed_s5_show_button_bashers.png",
      "version": "1629928444",
      "filesize": 583470,
      "base": "https://fallguys-assets.gamefuel.info/fallguys-uploads"
    },
    "id": "ui_newsfeed_s5_show_button_bashers"
  },
  {
    "dlc_item": {
      "path": "/1629928581/uploads/ui_newsfeed_s5_show_duos.png",
      "version": "1629928581",
      "filesize": 541510,
      "base": "https://fallguys-assets.gamefuel.info/fallguys-uploads"
    },
    "id": "ui_newsfeed_s5_show_duos"
  },
  {
    "dlc_item": {
      "path": "/1629928286/uploads/ui_newsfeed_s5_show_jungle.png",
      "version": "1629928286",
      "filesize": 682409,
      "base": "https://fallguys-assets.gamefuel.info/fallguys-uploads"
    },
    "id": "ui_newsfeed_s5_show_jungle"
  },
  {
    "dlc_item": {
      "path": "/1629928204/uploads/ui_newsfeed_s5_show_lily_leapers.png",
      "version": "1629928204",
      "filesize": 755085,
      "base": "https://fallguys-assets.gamefuel.info/fallguys-uploads"
    },
    "id": "ui_newsfeed_s5_show_lily_leapers"
  },
  {
    "dlc_item": {
      "path": "/1629928498/uploads/ui_newsfeed_s5_show_olympics.png",
      "version": "1629928498",
      "filesize": 598698,
      "base": "https://fallguys-assets.gamefuel.info/fallguys-uploads"
    },
    "id": "ui_newsfeed_s5_show_olympics"
  },
  {
    "dlc_item": {
      "path": "/1629928403/uploads/ui_newsfeed_s5_show_tiptoe.png",
      "version": "1629928403",
      "filesize": 649468,
      "base": "https://fallguys-assets.gamefuel.info/fallguys-uploads"
    },
    "id": "ui_newsfeed_s5_show_tiptoe"
  },
  {
    "dlc_item": {
      "path": "/1629928540/uploads/ui_newsfeed_s5_show_trios.png",
      "version": "1629928540",
      "filesize": 551778,
      "base": "https://fallguys-assets.gamefuel.info/fallguys-uploads"
    },
    "id": "ui_newsfeed_s5_show_trios"
  },
  {
    "dlc_item": {
      "path": "/1636109347/uploads/ui_newsfeed_s6_dove_04.png",
      "version": "1636109347",
      "filesize": 146017,
      "base": "https://fallguys-assets.gamefuel.info/fallguys-uploads"
    },
    "id": "ui_newsfeed_s6_dove_04"
  },
  {
    "dlc_item": {
      "path": "/1637708636/uploads/ui_newsfeed_s6_launch_key_art.png",
      "version": "1637708636",
      "filesize": 426440,
      "base": "https://fallguys-assets.gamefuel.info/fallguys-uploads"
    },
    "id": "ui_newsfeed_s6_launch_key_art"
  },
  {
    "dlc_item": {
      "path": "/1634824900/uploads/ui_newsfeed_s6_launch_party_dove.png",
      "version": "1634824900",
      "filesize": 137484,
      "base": "https://fallguys-assets.gamefuel.info/fallguys-uploads"
    },
    "id": "ui_newsfeed_s6_launch_party_dove"
  },
  {
    "dlc_item": {
      "path": "/1638291404/uploads/ui_newsfeed_s6_new_shows.png",
      "version": "1638291404",
      "filesize": 446023,
      "base": "https://fallguys-assets.gamefuel.info/fallguys-uploads"
    },
    "id": "ui_newsfeed_s6_new_shows"
  },
  {
    "dlc_item": {
      "path": "/1638291322/uploads/ui_newsfeed_s6_show_only_finals.png",
      "version": "1638291322",
      "filesize": 321274,
      "base": "https://fallguys-assets.gamefuel.info/fallguys-uploads"
    },
    "id": "ui_newsfeed_s6_show_only_finals"
  },
  {
    "dlc_item": {
      "path": "/1629928460/uploads/ui_newsfeed_screenshot_01.png",
      "version": "1629928460",
      "filesize": 799234,
      "base": "https://fallguys-assets.gamefuel.info/fallguys-uploads"
    },
    "id": "ui_newsfeed_screenshot_01"
  },
  {
    "dlc_item": {
      "path": "/1629928410/uploads/ui_newsfeed_screenshot_02.png",
      "version": "1629928410",
      "filesize": 777109,
      "base": "https://fallguys-assets.gamefuel.info/fallguys-uploads"
    },
    "id": "ui_newsfeed_screenshot_02"
  },
  {
    "dlc_item": {
      "path": "/1629928256/uploads/ui_newsfeed_screenshot_03.png",
      "version": "1629928256",
      "filesize": 815914,
      "base": "https://fallguys-assets.gamefuel.info/fallguys-uploads"
    },
    "id": "ui_newsfeed_screenshot_03"
  },
  {
    "dlc_item": {
      "path": "/1629928760/uploads/ui_newsfeed_screenshot_04.png",
      "version": "1629928760",
      "filesize": 664679,
      "base": "https://fallguys-assets.gamefuel.info/fallguys-uploads"
    },
    "id": "ui_newsfeed_screenshot_04"
  },
  {
    "dlc_item": {
      "path": "/1629928503/uploads/ui_newsfeed_screenshot_05.png",
      "version": "1629928503",
      "filesize": 739875,
      "base": "https://fallguys-assets.gamefuel.info/fallguys-uploads"
    },
    "id": "ui_newsfeed_screenshot_05"
  },
  {
    "dlc_item": {
      "path": "/1629928747/uploads/ui_newsfeed_screenshot_06.png",
      "version": "1629928747",
      "filesize": 660319,
      "base": "https://fallguys-assets.gamefuel.info/fallguys-uploads"
    },
    "id": "ui_newsfeed_screenshot_06"
  },
  {
    "dlc_item": {
      "path": "/1629928766/uploads/ui_newsfeed_screenshot_07.png",
      "version": "1629928766",
      "filesize": 681122,
      "base": "https://fallguys-assets.gamefuel.info/fallguys-uploads"
    },
    "id": "ui_newsfeed_screenshot_07"
  },
  {
    "dlc_item": {
      "path": "/1641481736/uploads/ui_newsfeed_show_only_races.png",
      "version": "1641481736",
      "filesize": 110999,
      "base": "https://fallguys-assets.gamefuel.info/fallguys-uploads"
    },
    "id": "ui_newsfeed_show_only_races"
  },
  {
    "dlc_item": {
      "path": "/1619013849/uploads/ui_newsfeed_sparrow_fame_event.png",
      "version": "1619013849",
      "filesize": 658836,
      "base": "https://fallguys-assets.gamefuel.info/fallguys-uploads"
    },
    "id": "ui_newsfeed_sparrow_fame_event"
  },
  {
    "dlc_item": {
      "path": "/1648117911/uploads/ui_newsfeed_squads.png",
      "version": "1648117911",
      "filesize": 459653,
      "base": "https://fallguys-assets.gamefuel.info/fallguys-uploads"
    },
    "id": "ui_newsfeed_squads"
  },
  {
    "dlc_item": {
      "path": "/1630409497/uploads/ui_newsfeed_sumfruit_1.png",
      "version": "1630409497",
      "filesize": 1827364,
      "base": "https://fallguys-assets.gamefuel.info/fallguys-uploads"
    },
    "id": "ui_newsfeed_sumfruit_1"
  },
  {
    "dlc_item": {
      "path": "/1630409506/uploads/ui_newsfeed_sumfruit_2.png",
      "version": "1630409506",
      "filesize": 2271524,
      "base": "https://fallguys-assets.gamefuel.info/fallguys-uploads"
    },
    "id": "ui_newsfeed_sumfruit_2"
  },
  {
    "dlc_item": {
      "path": "/1630409515/uploads/ui_newsfeed_sumfruit_3.png",
      "version": "1630409515",
      "filesize": 1804929,
      "base": "https://fallguys-assets.gamefuel.info/fallguys-uploads"
    },
    "id": "ui_newsfeed_sumfruit_3"
  },
  {
    "dlc_item": {
      "path": "/1638299104/uploads/ui_newsfeed_survey.png",
      "version": "1638299104",
      "filesize": 127676,
      "base": "https://fallguys-assets.gamefuel.info/fallguys-uploads"
    },
    "id": "ui_newsfeed_survey"
  },
  {
    "dlc_item": {
      "path": "/1638874870/uploads/ui_newsfeed_survey_s6.png",
      "version": "1638874870",
      "filesize": 199367,
      "base": "https://fallguys-assets.gamefuel.info/fallguys-uploads"
    },
    "id": "ui_newsfeed_survey_s6"
  },
  {
    "dlc_item": {
      "path": "/1633953343/uploads/ui_newsfeed_tanager.png",
      "version": "1633953343",
      "filesize": 55029,
      "base": "https://fallguys-assets.gamefuel.info/fallguys-uploads"
    },
    "id": "ui_newsfeed_tanager"
  },
  {
    "dlc_item": {
      "path": "/1630401779/uploads/ui_newsfeed_toucan_le.png",
      "version": "1630401779",
      "filesize": 1019719,
      "base": "https://fallguys-assets.gamefuel.info/fallguys-uploads"
    },
    "id": "ui_newsfeed_toucan_le"
  },
  {
    "dlc_item": {
      "path": "/1630401356/uploads/ui_newsfeed_toucan_quad.png",
      "version": "1630401356",
      "filesize": 1177429,
      "base": "https://fallguys-assets.gamefuel.info/fallguys-uploads"
    },
    "id": "ui_newsfeed_toucan_quad"
  },
  {
    "dlc_item": {
      "path": "/1630401920/uploads/ui_newsfeed_toucan_trio.png",
      "version": "1630401920",
      "filesize": 1126000,
      "base": "https://fallguys-assets.gamefuel.info/fallguys-uploads"
    },
    "id": "ui_newsfeed_toucan_trio"
  },
  {
    "dlc_item": {
      "path": "/1638460964/uploads/ui_newsfeed_vulture_costumes.png",
      "version": "1638460964",
      "filesize": 1891018,
      "base": "https://fallguys-assets.gamefuel.info/fallguys-uploads"
    },
    "id": "ui_newsfeed_vulture_costumes"
  },
  {
    "dlc_item": {
      "path": "/1638460958/uploads/ui_newsfeed_vulture_le.png",
      "version": "1638460958",
      "filesize": 1825013,
      "base": "https://fallguys-assets.gamefuel.info/fallguys-uploads"
    },
    "id": "ui_newsfeed_vulture_le"
  },
  {
    "dlc_item": {
      "path": "/1645459360/uploads/ui_newsfeed_week_of_romance.png",
      "version": "1645459360",
      "filesize": 178704,
      "base": "https://fallguys-assets.gamefuel.info/fallguys-uploads"
    },
    "id": "ui_newsfeed_week_of_romance"
  },
  {
    "dlc_item": {
      "path": "/1628784991/uploads/ui_reward_survey_qr.png",
      "version": "1628784991",
      "filesize": 2155118,
      "base": "https://fallguys-assets.gamefuel.info/fallguys-uploads"
    },
    "id": "ui_reward_survey_qr"
  },
  {
    "dlc_item": {
      "path": "/1629912297/uploads/ui_s4_amazon_may.png",
      "version": "1629912297",
      "filesize": 705294,
      "base": "https://fallguys-assets.gamefuel.info/fallguys-uploads"
    },
    "id": "ui_s4_amazon_may"
  },
  {
    "dlc_item": {
      "path": "/1620655926/uploads/ui_s4_among_us_alt.png",
      "version": "1620655926",
      "filesize": 883685,
      "base": "https://fallguys-assets.gamefuel.info/fallguys-uploads"
    },
    "id": "ui_s4_among_us_alt"
  },
  {
    "dlc_item": {
      "path": "/1630062266/uploads/ui_s4_show_blowup.png",
      "version": "1630062266",
      "filesize": 651817,
      "base": "https://fallguys-assets.gamefuel.info/fallguys-uploads"
    },
    "id": "ui_s4_show_blowup"
  },
  {
    "dlc_item": {
      "path": "/1630062251/uploads/ui_s4_show_hoverboard.png",
      "version": "1630062251",
      "filesize": 697912,
      "base": "https://fallguys-assets.gamefuel.info/fallguys-uploads"
    },
    "id": "ui_s4_show_hoverboard"
  },
  {
    "dlc_item": {
      "path": "/1630062288/uploads/ui_s4_show_low_grav_hex_a_gone.png",
      "version": "1630062288",
      "filesize": 549288,
      "base": "https://fallguys-assets.gamefuel.info/fallguys-uploads"
    },
    "id": "ui_s4_show_low_grav_hex_a_gone"
  },
  {
    "dlc_item": {
      "path": "/1630062273/uploads/ui_s4_show_mix_it_up.png",
      "version": "1630062273",
      "filesize": 567452,
      "base": "https://fallguys-assets.gamefuel.info/fallguys-uploads"
    },
    "id": "ui_s4_show_mix_it_up"
  },
  {
    "dlc_item": {
      "path": "/1630062245/uploads/ui_s4_show_no_teams.png",
      "version": "1630062245",
      "filesize": 562199,
      "base": "https://fallguys-assets.gamefuel.info/fallguys-uploads"
    },
    "id": "ui_s4_show_no_teams"
  },
  {
    "dlc_item": {
      "path": "/1630062258/uploads/ui_s4_show_slimescraper_time.png",
      "version": "1630062258",
      "filesize": 681726,
      "base": "https://fallguys-assets.gamefuel.info/fallguys-uploads"
    },
    "id": "ui_s4_show_slimescraper_time"
  },
  {
    "dlc_item": {
      "path": "/1630062282/uploads/ui_s4_show_xtreme.png",
      "version": "1630062282",
      "filesize": 492550,
      "base": "https://fallguys-assets.gamefuel.info/fallguys-uploads"
    },
    "id": "ui_s4_show_xtreme"
  },
  {
    "dlc_item": {
      "path": "/1626781736/uploads/ui_s5_store_icon.png",
      "version": "1626781736",
      "filesize": 853496,
      "base": "https://fallguys-assets.gamefuel.info/fallguys-uploads"
    },
    "id": "ui_s5_store_icon"
  },
  {
    "dlc_item": {
      "path": "/1629928896/uploads/ui_slide_crown.png",
      "version": "1629928896",
      "filesize": 1127676,
      "base": "https://fallguys-assets.gamefuel.info/fallguys-uploads"
    },
    "id": "ui_slide_crown"
  },
  {
    "dlc_item": {
      "path": "/1629928387/uploads/ui_slide_rewards.png",
      "version": "1629928387",
      "filesize": 1013421,
      "base": "https://fallguys-assets.gamefuel.info/fallguys-uploads"
    },
    "id": "ui_slide_rewards"
  },
  {
    "dlc_item": {
      "path": "/1629928871/uploads/ui_slide_welcome.png",
      "version": "1629928871",
      "filesize": 1165160,
      "base": "https://fallguys-assets.gamefuel.info/fallguys-uploads"
    },
    "id": "ui_slide_welcome"
  },
  {
    "dlc_item": {
      "path": "/1626783448/uploads/ui_store_banner.png",
      "version": "1626783448",
      "filesize": 853496,
      "base": "https://fallguys-assets.gamefuel.info/fallguys-uploads"
    },
    "id": "ui_store_banner"
  }
]