[
  {
    "id": "blunderdome_palette",
    "palette_name": "Blunderdome",
    "colours": [
      {
        "hex_color_code": "#F4FAE2"
      },
      {
        "hex_color_code": "#99E1FF"
      },
      {
        "hex_color_code": "#8CADF0"
      },
      {
        "hex_color_code": "#6181F6"
      },
      {
        "hex_color_code": "#01ACEF"
      },
      {
        "hex_color_code": "#0080E4"
      },
      {
        "hex_color_code": "#3F49DB"
      },
      {
        "hex_color_code": "#9C6BF8"
      },
      {
        "hex_color_code": "#4CBA75"
      },
      {
        "hex_color_code": "#FECC86"
      },
      {
        "hex_color_code": "#FFCC52"
      },
      {
        "hex_color_code": "#FFA55A"
      },
      {
        "hex_color_code": "#FF7158"
      },
      {
        "hex_color_code": "#B76E4F"
      },
      {
        "hex_color_code": "#FF3C3C"
      },
      {
        "hex_color_code": "#FB2178"
      },
      {
        "hex_color_code": "#F1F2F3"
      },
      {
        "hex_color_code": "#B5BBC2"
      },
      {
        "hex_color_code": "#6D7884"
      },
      {
        "hex_color_code": "#2E3237"
      }
    ],
    "localised_name": "localised_strings.wle_colour_palette_blunderdome"
  },
  {
    "id": "festival_palette",
    "palette_name": "Festival",
    "colours": [
      {
        "hex_color_code": "#F5F0D7"
      },
      {
        "hex_color_code": "#44C5FA"
      },
      {
        "hex_color_code": "#46A9EB"
      },
      {
        "hex_color_code": "#5093FF"
      },
      {
        "hex_color_code": "#007CFC"
      },
      {
        "hex_color_code": "#95E6C5"
      },
      {
        "hex_color_code": "#80C7DB"
      },
      {
        "hex_color_code": "#AF5EC6"
      },
      {
        "hex_color_code": "#FFE250"
      },
      {
        "hex_color_code": "#FCCB22"
      },
      {
        "hex_color_code": "#FAB500"
      },
      {
        "hex_color_code": "#FA9C57"
      },
      {
        "hex_color_code": "#FF95DA"
      },
      {
        "hex_color_code": "#FB57C7"
      },
      {
        "hex_color_code": "#FF529D"
      },
      {
        "hex_color_code": "#FF1583"
      },
      {
        "hex_color_code": "#F3F1F3"
      },
      {
        "hex_color_code": "#C2B5C1"
      },
      {
        "hex_color_code": "#846D82"
      },
      {
        "hex_color_code": "#372E36"
      }
    ],
    "localised_name": "localised_strings.wle_colour_palette_festival"
  },
  {
    "id": "future_palette",
    "palette_name": "Future",
    "colours": [
      {
        "hex_color_code": "#80E5FF"
      },
      {
        "hex_color_code": "#42BDFF"
      },
      {
        "hex_color_code": "#527EED"
      },
      {
        "hex_color_code": "#AD79FF"
      },
      {
        "hex_color_code": "#7845AD"
      },
      {
        "hex_color_code": "#43125C"
      },
      {
        "hex_color_code": "#80F5D9"
      },
      {
        "hex_color_code": "#C9FFB2"
      },
      {
        "hex_color_code": "#FF54DD"
      },
      {
        "hex_color_code": "#E432C7"
      },
      {
        "hex_color_code": "#FF7171"
      },
      {
        "hex_color_code": "#F41270"
      },
      {
        "hex_color_code": "#8290B2"
      },
      {
        "hex_color_code": "#5A6186"
      },
      {
        "hex_color_code": "#293150"
      },
      {
        "hex_color_code": "#0A0416"
      },
      {
        "hex_color_code": "#F3F1F3"
      },
      {
        "hex_color_code": "#C2B5C1"
      },
      {
        "hex_color_code": "#846D82"
      },
      {
        "hex_color_code": "#372E36"
      }
    ],
    "localised_name": "localised_strings.wle_colour_palette_future"
  },
  {
    "id": "halloween_palette",
    "palette_name": "Halloween",
    "colours": [
      {
        "hex_color_code": "#42DDF8"
      },
      {
        "hex_color_code": "#4F1FFF"
      },
      {
        "hex_color_code": "#856DFF"
      },
      {
        "hex_color_code": "#B300FF"
      },
      {
        "hex_color_code": "#8D0095"
      },
      {
        "hex_color_code": "#5605AA"
      },
      {
        "hex_color_code": "#260245"
      },
      {
        "hex_color_code": "#B4FE86"
      },
      {
        "hex_color_code": "#45CEA0"
      },
      {
        "hex_color_code": "#FDCF2B"
      },
      {
        "hex_color_code": "#FFAA00"
      },
      {
        "hex_color_code": "#FF6F00"
      },
      {
        "hex_color_code": "#FF2D00"
      },
      {
        "hex_color_code": "#7C6571"
      },
      {
        "hex_color_code": "#6C555C"
      },
      {
        "hex_color_code": "#5F3F41"
      },
      {
        "hex_color_code": "#F3F1F3"
      },
      {
        "hex_color_code": "#C2B5C1"
      },
      {
        "hex_color_code": "#846D82"
      },
      {
        "hex_color_code": "#372E36"
      }
    ],
    "localised_name": "localised_strings.wle_colour_palette_falloween"
  },
  {
    "id": "jungle_palette",
    "palette_name": "Jungle",
    "colours": [
      {
        "hex_color_code": "#5AC0F0"
      },
      {
        "hex_color_code": "#1FA7FD"
      },
      {
        "hex_color_code": "#D3EA3A"
      },
      {
        "hex_color_code": "#9FCB26"
      },
      {
        "hex_color_code": "#6ED025"
      },
      {
        "hex_color_code": "#5DB41D"
      },
      {
        "hex_color_code": "#5B9A0C"
      },
      {
        "hex_color_code": "#FFD16E"
      },
      {
        "hex_color_code": "#FFBD31"
      },
      {
        "hex_color_code": "#FD9C00"
      },
      {
        "hex_color_code": "#F68720"
      },
      {
        "hex_color_code": "#FE611E"
      },
      {
        "hex_color_code": "#AF5D38"
      },
      {
        "hex_color_code": "#F788BB"
      },
      {
        "hex_color_code": "#F8519F"
      },
      {
        "hex_color_code": "#EE413B"
      },
      {
        "hex_color_code": "#F2F2F2"
      },
      {
        "hex_color_code": "#BBBDBA"
      },
      {
        "hex_color_code": "#787B75"
      },
      {
        "hex_color_code": "#323331"
      }
    ],
    "localised_name": "localised_strings.wle_colour_palette_jungle"
  },
  {
    "id": "junkyard_palette",
    "palette_name": "Junkyard",
    "colours": [
      {
        "hex_color_code": "#BAEFFC"
      },
      {
        "hex_color_code": "#9271C2"
      },
      {
        "hex_color_code": "#9153E5"
      },
      {
        "hex_color_code": "#C4E8DC"
      },
      {
        "hex_color_code": "#21E1DA"
      },
      {
        "hex_color_code": "#77D818"
      },
      {
        "hex_color_code": "#34B394"
      },
      {
        "hex_color_code": "#F9F940"
      },
      {
        "hex_color_code": "#FFBE0B"
      },
      {
        "hex_color_code": "#EAC5B0"
      },
      {
        "hex_color_code": "#B37C49"
      },
      {
        "hex_color_code": "#FF8434"
      },
      {
        "hex_color_code": "#FF5D00"
      },
      {
        "hex_color_code": "#F3B9DF"
      },
      {
        "hex_color_code": "#F15BB5"
      },
      {
        "hex_color_code": "#FF006E"
      },
      {
        "hex_color_code": "#F1F3F2"
      },
      {
        "hex_color_code": "#A9CCCC"
      },
      {
        "hex_color_code": "#517571"
      },
      {
        "hex_color_code": "#1E2628"
      }
    ],
    "localised_name": "localised_strings.wle_colour_palette_junkyard"
  },
  {
    "id": "medieval_palette",
    "palette_name": "Medieval",
    "colours": [
      {
        "hex_color_code": "#F8BEE3"
      },
      {
        "hex_color_code": "#BA8BFA"
      },
      {
        "hex_color_code": "#9C6BF8"
      },
      {
        "hex_color_code": "#922DAD"
      },
      {
        "hex_color_code": "#CCD063"
      },
      {
        "hex_color_code": "#C0C432"
      },
      {
        "hex_color_code": "#8FB76E"
      },
      {
        "hex_color_code": "#4CBA75"
      },
      {
        "hex_color_code": "#F4CD43"
      },
      {
        "hex_color_code": "#EDB500"
      },
      {
        "hex_color_code": "#FB9711"
      },
      {
        "hex_color_code": "#F39872"
      },
      {
        "hex_color_code": "#B76E4F"
      },
      {
        "hex_color_code": "#F3634D"
      },
      {
        "hex_color_code": "#DA4470"
      },
      {
        "hex_color_code": "#F53012"
      },
      {
        "hex_color_code": "#F6EEF6"
      },
      {
        "hex_color_code": "#BFB7BF"
      },
      {
        "hex_color_code": "#7C757C"
      },
      {
        "hex_color_code": "#362E35"
      }
    ],
    "localised_name": "localised_strings.wle_colour_palette_medieval"
  },
  {
    "id": "retro_palette",
    "palette_name": "Retro",
    "colours": [
      {
        "hex_color_code": "#FFFFFF"
      },
      {
        "hex_color_code": "#DDDDDD"
      },
      {
        "hex_color_code": "#B3B3B3"
      },
      {
        "hex_color_code": "#868686"
      },
      {
        "hex_color_code": "#85B6FF"
      },
      {
        "hex_color_code": "#C2A5EA"
      },
      {
        "hex_color_code": "#9485A8"
      },
      {
        "hex_color_code": "#BAF4EC"
      },
      {
        "hex_color_code": "#76EADA"
      },
      {
        "hex_color_code": "#63D3DA"
      },
      {
        "hex_color_code": "#FFFDA0"
      },
      {
        "hex_color_code": "#FFD68C"
      },
      {
        "hex_color_code": "#FFAA75"
      },
      {
        "hex_color_code": "#FFA0A5"
      },
      {
        "hex_color_code": "#FF95D6"
      },
      {
        "hex_color_code": "#FF70C4"
      },
      {
        "hex_color_code": "#F6EEF6"
      },
      {
        "hex_color_code": "#BFB7BF"
      },
      {
        "hex_color_code": "#7C757C"
      },
      {
        "hex_color_code": "#362E35"
      }
    ],
    "localised_name": "localised_strings.wle_colour_palette_digital"
  },
  {
    "id": "space_palette",
    "palette_name": "Space",
    "colours": [
      {
        "hex_color_code": "#D4E8F1"
      },
      {
        "hex_color_code": "#089FF5"
      },
      {
        "hex_color_code": "#0A72C8"
      },
      {
        "hex_color_code": "#065AA9"
      },
      {
        "hex_color_code": "#F200F4"
      },
      {
        "hex_color_code": "#5A46A9"
      },
      {
        "hex_color_code": "#382C70"
      },
      {
        "hex_color_code": "#151137"
      },
      {
        "hex_color_code": "#BFC2B9"
      },
      {
        "hex_color_code": "#11ECE9"
      },
      {
        "hex_color_code": "#7ABE81"
      },
      {
        "hex_color_code": "#F5C581"
      },
      {
        "hex_color_code": "#FAB41A"
      },
      {
        "hex_color_code": "#F98F39"
      },
      {
        "hex_color_code": "#FF5462"
      },
      {
        "hex_color_code": "#F98F39"
      },
      {
        "hex_color_code": "#FFFFFF"
      },
      {
        "hex_color_code": "#E6E9DE"
      },
      {
        "hex_color_code": "#4C4C4C"
      },
      {
        "hex_color_code": "#000000"
      }
    ],
    "localised_name": "localised_strings.wle_colour_palette_space"
  },
  {
    "id": "underwater_palette",
    "palette_name": "Underwater",
    "colours": [
      {
        "hex_color_code": "#FFFFFF"
      },
      {
        "hex_color_code": "#25C2FD"
      },
      {
        "hex_color_code": "#0C3EA0"
      },
      {
        "hex_color_code": "#45EBEF"
      },
      {
        "hex_color_code": "#79FEBF"
      },
      {
        "hex_color_code": "#17D3AF"
      },
      {
        "hex_color_code": "#17BA83"
      },
      {
        "hex_color_code": "#FFE50E"
      },
      {
        "hex_color_code": "#FFD05B"
      },
      {
        "hex_color_code": "#FFBE3D"
      },
      {
        "hex_color_code": "#E7A029"
      },
      {
        "hex_color_code": "#FF6819"
      },
      {
        "hex_color_code": "#FE856A"
      },
      {
        "hex_color_code": "#FDB5C3"
      },
      {
        "hex_color_code": "#FF7896"
      },
      {
        "hex_color_code": "#FF3460"
      },
      {
        "hex_color_code": "#EAECEE"
      },
      {
        "hex_color_code": "#A5B5B9"
      },
      {
        "hex_color_code": "#617B81"
      },
      {
        "hex_color_code": "#283336"
      }
    ],
    "localised_name": "localised_strings.wle_colour_palette_underwater"
  },
  {
    "id": "vanilla_palette",
    "palette_name": "Vanilla",
    "colours": [
      {
        "hex_color_code": "#75D1FF"
      },
      {
        "hex_color_code": "#519BEC"
      },
      {
        "hex_color_code": "#107DF4"
      },
      {
        "hex_color_code": "#7979FF"
      },
      {
        "hex_color_code": "#8640F3"
      },
      {
        "hex_color_code": "#C357BA"
      },
      {
        "hex_color_code": "#FF91F9"
      },
      {
        "hex_color_code": "#7DE2C1"
      },
      {
        "hex_color_code": "#00D99C"
      },
      {
        "hex_color_code": "#D1FF74"
      },
      {
        "hex_color_code": "#FEF57C"
      },
      {
        "hex_color_code": "#FCCB22"
      },
      {
        "hex_color_code": "#FF8E38"
      },
      {
        "hex_color_code": "#FF5358"
      },
      {
        "hex_color_code": "#FF4197"
      },
      {
        "hex_color_code": "#E90069"
      },
      {
        "hex_color_code": "#F6EEF6"
      },
      {
        "hex_color_code": "#BFB7BF"
      },
      {
        "hex_color_code": "#7C757C"
      },
      {
        "hex_color_code": "#362E35"
      }
    ],
    "localised_name": "localised_strings.wle_colour_palette_original"
  },
  {
    "id": "volcano_palette",
    "palette_name": "Volcano",
    "colours": [
      {
        "hex_color_code": "#FFBE3D"
      },
      {
        "hex_color_code": "#3C9DFF"
      },
      {
        "hex_color_code": "#086DFF"
      },
      {
        "hex_color_code": "#E69BFF"
      },
      {
        "hex_color_code": "#667AFF"
      },
      {
        "hex_color_code": "#844ADF"
      },
      {
        "hex_color_code": "#392793"
      },
      {
        "hex_color_code": "#E7A029"
      },
      {
        "hex_color_code": "#FFD05B"
      },
      {
        "hex_color_code": "#FF6819"
      },
      {
        "hex_color_code": "#FE856A"
      },
      {
        "hex_color_code": "#FDB5C3"
      },
      {
        "hex_color_code": "#FF7896"
      },
      {
        "hex_color_code": "#FF3460"
      },
      {
        "hex_color_code": "#FF41B9"
      },
      {
        "hex_color_code": "#BD0270"
      },
      {
        "hex_color_code": "#F3F1F3"
      },
      {
        "hex_color_code": "#C2B5C1"
      },
      {
        "hex_color_code": "#846D82"
      },
      {
        "hex_color_code": "#372E36"
      }
    ],
    "localised_name": "localised_strings.wle_colour_palette_volcano"
  },
  {
    "id": "winter_palette",
    "palette_name": "Winter",
    "colours": [
      {
        "hex_color_code": "#FFFFFF"
      },
      {
        "hex_color_code": "#7ED4FF"
      },
      {
        "hex_color_code": "#5DA4F3"
      },
      {
        "hex_color_code": "#0080DE"
      },
      {
        "hex_color_code": "#7979FF"
      },
      {
        "hex_color_code": "#A5A5FF"
      },
      {
        "hex_color_code": "#81F2F6"
      },
      {
        "hex_color_code": "#7DE2C1"
      },
      {
        "hex_color_code": "#00D99C"
      },
      {
        "hex_color_code": "#FFFABE"
      },
      {
        "hex_color_code": "#FEF57C"
      },
      {
        "hex_color_code": "#F5C755"
      },
      {
        "hex_color_code": "#FF8589"
      },
      {
        "hex_color_code": "#FAD8ED"
      },
      {
        "hex_color_code": "#FB80C5"
      },
      {
        "hex_color_code": "#FF4197"
      },
      {
        "hex_color_code": "#F6EEF6"
      },
      {
        "hex_color_code": "#BFB7BF"
      },
      {
        "hex_color_code": "#7C757C"
      },
      {
        "hex_color_code": "#362E35"
      }
    ],
    "localised_name": "localised_strings.wle_colour_palette_winter"
  }
]