[
  {
    "show_id": "live_event_symphony_launch_show_template",
    "min_match_size": 32,
    "is_sbmm_enabled": false,
    "id": "gate_ss2_stadium_stars"
  },
  {
    "show_id": "event_blast_ball_banger_template",
    "min_match_size": 22,
    "is_sbmm_enabled": false,
    "id": "ss2_gate_blast_ball_bangers"
  },
  {
    "show_id": "event_only_blast_ball_trials_template",
    "min_match_size": 20,
    "is_sbmm_enabled": false,
    "id": "ss2_gate_blast_ball_trials"
  },
  {
    "show_id": "event_yeetus_template",
    "min_match_size": 40,
    "is_sbmm_enabled": false,
    "id": "ss2_gate_clan_yeetus_show"
  },
  {
    "show_id": "event_only_fall_ball_template",
    "min_match_size": 40,
    "is_sbmm_enabled": false,
    "id": "ss2_gate_fall_ball_cup"
  },
  {
    "show_id": "event_fan_favourites_template",
    "min_match_size": 40,
    "is_sbmm_enabled": false,
    "id": "ss2_gate_fan_favourites"
  },
  {
    "show_id": "event_only_finals_template",
    "min_match_size": 40,
    "is_sbmm_enabled": false,
    "id": "ss2_gate_finals_marathon"
  },
  {
    "show_id": "event_only_floor_fall_template",
    "min_match_size": 40,
    "is_sbmm_enabled": false,
    "id": "ss2_gate_hex_a_gone"
  },
  {
    "show_id": "event_only_jump_club_template",
    "min_match_size": 24,
    "is_sbmm_enabled": false,
    "id": "ss2_gate_jump_around"
  },
  {
    "show_id": "event_only_drumtop_template",
    "min_match_size": 32,
    "is_sbmm_enabled": false,
    "id": "ss2_gate_lily_leaper_trials"
  },
  {
    "show_id": "event_only_floor_fall_low_grav",
    "min_match_size": 16,
    "is_sbmm_enabled": false,
    "id": "ss2_gate_low_gravity_hexagone"
  },
  {
    "show_id": "squads_2player_template",
    "min_match_size": 40,
    "is_sbmm_enabled": false,
    "id": "ss2_gate_mainshow_duos"
  },
  {
    "show_id": "main_show",
    "min_match_size": 40,
    "is_sbmm_enabled": false,
    "id": "ss2_gate_mainshow_solo"
  },
  {
    "show_id": "squads_4player",
    "min_match_size": 40,
    "is_sbmm_enabled": false,
    "id": "ss2_gate_mainshow_squads"
  },
  {
    "show_id": "event_pixel_palooza_template",
    "min_match_size": 40,
    "is_sbmm_enabled": false,
    "id": "ss2_gate_pixel_palooza"
  },
  {
    "show_id": "event_only_skeefall_timetrial_s6_1",
    "min_match_size": 40,
    "is_sbmm_enabled": false,
    "id": "ss2_gate_ski_fall_high_scorers"
  },
  {
    "show_id": "event_only_slime_climb",
    "min_match_size": 40,
    "is_sbmm_enabled": false,
    "id": "ss2_gate_slime_climb_time"
  },
  {
    "show_id": "event_autumn_festival_squads_template",
    "min_match_size": 40,
    "is_sbmm_enabled": false,
    "id": "ss2_gate_squads_festival"
  },
  {
    "show_id": "event_squads_survival_template",
    "min_match_size": 40,
    "is_sbmm_enabled": false,
    "id": "ss2_gate_squads_survival"
  },
  {
    "show_id": "show_robotrampage_ss2_show1_template",
    "min_match_size": 40,
    "is_sbmm_enabled": false,
    "id": "ss2_gate_stomping_ground_standoff"
  },
  {
    "show_id": "event_only_survival_template",
    "min_match_size": 40,
    "is_sbmm_enabled": false,
    "id": "ss2_gate_survival_of_the_fittest"
  },
  {
    "show_id": "event_only_tip_toe_template",
    "min_match_size": 20,
    "is_sbmm_enabled": false,
    "id": "ss2_gate_tip_toe_trials"
  },
  {
    "show_id": "event_xtreme_fall_guys_template",
    "min_match_size": 40,
    "is_sbmm_enabled": false,
    "id": "ss2_gate_xtreme_solo_show"
  },
  {
    "show_id": "event_walnut_template",
    "min_match_size": 16,
    "is_sbmm_enabled": false,
    "id": "ss2_schedule_hex_a_thon_games"
  }
]